code
   argcount 0
   nlocals 0
   stacksize 3419
   flags 0040
   code
      6400006401006c00005a0000640200640300640400640500640600640700
      640800640900640a00640b00640c00640d00640e00640f00641000641100
      641200641100641300641400641500641600641700641800641900641400
      641a00641b00641c00641d00641e00641f00642000642100642200642300
      642400642500641b00642600642700642800642900642a00642b00642c00
      642d00642e00642f00643000643100643200643300643400643500643600
      640e00643700643800643900643a00643b00643c00643d00641e00641b00
      643e00643f00644000644100641100641f00644200644300644400640900
      644500641600644600644700644800644900644100644a00644b00644c00
      644d00641400644e00644f00645000640800645100641400645200641600
      644300645300645400642400645500645600645700645800645900645a00
      645b00641700645c00645d00642000645e00645f00642300646000646100
      645d00646200646300646400644600646100646500646600646700646800
      646900646900646a00646b00645b00646c00645b00646d00644100646e00
      646400645200640300643c00644700646f00647000647100647200643500
      646200647300647400647500647600642300647700646a00647800647900
      647a00640700647b00644800647c00647d00647e00642100647f00645700
      648000644400643300647800642100648100648200648300641700644900
      648400642e00648500641600648600640300648700646700646b00645a00
      648800641e00642f00648900642800648a00640e00648b00648c00648d00
      648e00643700645100648f00649000649100649200648400646700642000
      647300649300648e00647600649400649500649500649600646a00649700
      649800649900643500649a00649b00649c00645b00643600649000649d00
      649e00641500647a00649f0064a00064300064020064a10064350064a200
      64510064a300643d00643f0064810064570064040064490064830064a400
      645c00644a00644400641c00649500642a00647500644c0064150064a500
      640f0064a60064050064190064a700640800642c00647700645e0064a800
      648f00640e0064a90064070064aa00641200643000649f00646a00645e00
      643800642600647b00641900645700649200649300642200642100649500
      649600642000645500647c0064ab0064ac00644f00649c0064820064ad00
      64200064ae0064af00642100642c00642d00643400642f00648600649b00
      643200648200642e0064350064ac00647f0064650064b000644600644c00
      646900642300643d0064b10064af00647900649500640d00644400641100
      64b20064b300649e00644d00643d0064390064b40064b500649400644300
      645c0064b60064b70064b800641000647600645300643a00644600641b00
      644a0064510064780064990064b90064ba00649d00644200647800640e00
      64bb0064bc0064bd0064be00649900643d00649300646300645a0064bf00
      645e00646b0064ab00646900646100649d0064640064630064c00064bd00
      64610064080064710064110064c100648f00648500646a00645f00646c00
      646c0064170064c20064410064b80064bd0064520064490064c300644700
      642500646c00642c00645e0064420064120064730064c400645d0064c500
      64230064c600646a0064b20064bc00647a0064c70064c800648b00642f00
      649a0064c90064b200648200645a0064470064440064ca0064cb00642000
      646600648c00647f0064cc0064c00064110064620064cd00646100644f00
      640300643000640500646b0064570064ce00641e00642f00648900642800
      644800649c0064cc00646a0064b500648e0064810064cf0064a700643300
      646500649100641100646700646a0064320064830064a80064d000647b00
      644e00642f0064d100640200643c00646900647f00642f0064d20064cb00
      64630064a00064ce00649000641c00643200645600642500649a0064c700
      640a0064890064a10064390064d300642f00643900643d00644e0064be00
      645a0064b30064490064a10064020064490064340064810064a000649500
      64d40064b200646d0064d500645e00640300641f0064d60064060064d200
      640800640900645f0064c200640c00643a00641d00645f0064a90064d600
      641200646700641100646a0064d70064d60064260064d800647400645700
      649b00640a0064c300641d0064d90064da0064200064560064d20064ab00
      64240064db00644f0064b70064ad0064580064bf00649c0064a200641800
      644b0064a000649100641a0064dc0064c100645e00641f00642e0064dc00
      647e00649e0064590064370064510064d40064dd0064de00641e0064c400
      64df00643f0064600064e000642800645d0064b300649e00644d00643d00
      64dd0064b40064b500649400643800645c00642d0064be00643a00649400
      64c50064a80064e100644900645600648c0064e200640b00643300640c00
      646600649d00644400644000640e0064e300646b0064bd0064e400643f00
      643d0064e300649a0064a200647e0064e500645f00649000649200642e00
      64380064660064510064c00064c70064d80064c60064b500646700642d00
      643b0064690064d000644200642600646c0064d60064600064410064a700
      64e600645200644900649800644700646f0064e700646800647200641c00
      648000647300642a0064710064760064e80064cd0064e90064dc00649b00
      64bb0064ea0064c80064cc00642f00643900643e0064b20064170064cb00
      64470064dd00649900645a0064b700648e00648c0064dd0064eb0064a600
      64050064ec0064780064180064630064ae00640c00641b00645f00645700
      647e00641e0064630064260064280064720064110064cc0064020064b000
      64e800643700642f00645300649000649200644d0064b700647400646900
      64730064840064ed0064ce0064e90064810064510064710064080064ee00
      64e40064ef0064430064d10064cd0064670064660064f00064e800649d00
      64b00064ae0064bb0064c10064de0064e300644a0064a100644300646600
      64ab00647200643d00648e00649800645a0064ab00646200648300647100
      642b00646f00643c0064390064950064f10064b200646d00649700645200
      64ae0064270064050064f200648100647b0064090064950064820064f300
      640d0064430064cb00641a0064110064120064e30064a00064d30064f200
      647e0064d00064c400646800645a0064eb00641b0064220064b500649100
      642800642000642100641000642f0064870064c40064ef00645b0064bd00
      64e60064ae00649c0064f400642c00641300648000642f00641a0064f500
      64f60064760064c70064450064d40064bf0064370064590064460064c200
      64950064ee00643d00641e00649c0064c60064470064900064ed00640500
      64660064ab0064430064a80064090064450064b40064250064070064ef00
      64b50064810064210064690064c30064850064530064e100644f00641b00
      64ca00641c00647800643300641600644f0064cb0064130064c90064da00
      64bb00647200646600641d00645a00643d00645d00642a0064a20064b700
      645e00640d0064ab00642d0064b20064a20064680064120064c00064c700
      64610064080064e40064670064c100643b0064e900646a00646d0064da00
      64680064260064e80064410064ab00643d0064520064690064b600649400
      646f0064db0064bd0064d900640d00647a00649e0064f100648b0064c500
      64c20064070064ab00643f0064bc0064e600645800647b00647500642f00
      64d10064c60064b20064260064140064900064ee0064c600640200642000
      648500646a0064e300646700645c00647300646200644200646f00644f00
      64f700640b00641b0064540064d00064530064b10064350064b900645b00
      64d20064f800645b00648c0064de00648e00643700644b00646b00649000
      64a800641c0064b700646700648c00641100649300644c00643600649400
      644e0064600064960064020064b600649800647f0064390064ea0064cb00
      64bb0064480064cb0064e60064c800642a0064a200647a0064c10064f100
      64300064f90064640064b90064f400642f0064cf0064d60064c80064c200
      64570064b30064a60064c70064ad0064f100646f00644400645900646900
      64b100647300649400645200648600640a00643d00642800640600640700
      64080064db0064b30064c50064080064e200640e00645f00641000641600
      648400647a00644f00641000642d0064e700644800642500641900645700
      64eb0064840064b300641d00641e00642800649c0064630064df00648100
      64570064b000649c0064260064ad00640400648a00649e00646c00642c00
      644b00642e00645f0064f70064f500643200645e00643d00643900645e00
      64f20064390064430064370064c200643f0064ee00643d00641e00648300
      640c00644e0064b600649100647d0064350064ab00644300644d00643200
      64710064b400642500644700646f00649e0064ee00644a0064b800649400
      64870064fa0064d500644f00641b00648c00649800641e00643300641600
      644300649d0064fb00642400640e0064cc00645700646800647a00645a00
      643d0064670064d300644800646c0064760064e80064920064a300643700
      64ae0064a400646300643d0064c70064d30064fc0064b00064bf0064b100
      649100649100646a00646d0064da0064700064fd0064e80064410064e800
      64090064ca00646d00649800644e00646f0064ba0064a000643f00648d00
      640400646c00646300645d0064760064c20064fa0064e800646a0064bc00
      647a0064ea00647b00640e0064e20064d100647e0064b200648a00642400
      64cb0064ee00643300645a0064040064230064980064ad00648a00641100
      648400643d0064b80064d60064a100641a00648700647000648e00648c00
      64fa00649500647a00645b0064a20064a40064a60064b700640a00645c00
      649400649a0064c200647600647c0064940064a900648300648900644e00
      64350064b10064c80064ca00648f0064d40064b60064c000643600645400
      640c0064170064630064250064c80064ef00644a0064d00064720064bc00
      649f00647f0064e700649e0064340064f80064da0064610064670064dd00
      641c0064cf00643d00644e0064b60064570064b30064a60064830064c400
      64a600646f0064440064cc00649500642a0064b20064410064820064a500
      64030064040064fd0064060064070064c800642e00640a0064170064f300
      640d0064a10064e900641000641100645d0064ea00649f00646a00641500
      64160064430064b40064790064570064eb00641b00647800646600646a00
      64b10064620064a40064330064790064b30064ae00646600645900647400
      646200647a0064660064e600640e00649b0064110064f30064b600648e00
      64bb00648d00644800641600643f0064ec00648b0064260064ae0064fe00
      64080064ce00640e00648e00640500644100648c0064a800649900644900
      645b0064820064cc0064900064f200644a00649600645000646a0064b100
      64800064f80064800064e500643600647200648e0064a80064170064f100
      64f70064a80064e90064440064e40064cc00646000640c00640d00645c00
      644300646b0064830064f90064f50064250064d60064ba00645000646800
      64c200648700641c00643f0064d30064ae0064630064a60064fd0064fd00
      649f00649b0064ad00645d00646200640d00646b0064e80064d40064af00
      641800647a0064a90064b30064230064710064ac0064b800643a00644400
      642c0064250064e700648f0064940064a40064620064f20064c000646b00
      64f700646500644700643f00644c0064290064e700643b0064270064f300
      64830064720064450064590064a700646a0064ce0064a30064b800646200
      640b00649400649a0064e40064d800640900642000649d00645c0064ff00
      645100640b00641b00646b0064780064220064850064430064b900642800
      645d0064050064cc00648c00649e0064c60064370064cf0064a700649000
      64360064910064b700646700646a0064e700642b0064a80064ce00649400
      640b00648f0064c10064fb0064c30064d900646c0064210064800064dc00
      646700645b0064cb00643a0064760064620064700064f60064800064a000
      64300064f90064a100644f0064bf00642f0064cf00643d00644e00649800
      64020064100064a00064cc0064960064a600646f00644b00643e00649500
      642a0064b200640a0064fa00649500640c0064c000644a0064b50064e200
      64c600642a0064c90064030064c50064420064730064910064e00064ff00
      64f200642600647d0064980064520064f000641100641700642b0064c600
      64ed0064e600640b0064db0064530064090064e300647f00648700640f00
      64150064f60064000164d600646100649f0064490064fd00641800642e00
      646e00647f0064c20064910064bc0064fd00644b00641d0064290064a500
      64200064460064ff00647000647b0064030064220064b900649b00642a00
      64eb0064dc00640200649900643400649a0064f30064630064cd0064ec00
      64bd0064480064be0064eb0064290064e70064330064320064d500648c00
      64810064d90064fb0064620064ec0064d00064e20064880064fa00647400
      642700647800646a00648700644600644300647c0064460064e300647c00
      64190064800064800064b10064f400649900648f00647c0064a30064f400
      64120064ec0064aa0064490064bd0064d30064780064dd0064090064bf00
      64cd0064950064ac0064420064bf00647500646700643b00647e00643100
      64f90064ee00649d0064720064ee00642c0064040064be00646000645100
      643d00647000642a0064010164fc00641c00643000640200645f00645200
      64b10064290064070064260064e20064d100647e0064b20064d800645a00
      64470064ee00643300642400647f00648500648c00647f00646700648b00
      64750064fd0064a50064bd0064a10064c20064ed0064b90064850064cb00
      647200646b0064630064db00644a0064340064840064e700643f00649300
      642d0064ea0064440064a70064900064910064a30064bf00646700646a00
      64730064f600644d00648700649400644e0064510064670064d70064d900
      649800647f00644300645d0064140064de0064bd0064e200644d00645f00
      642e0064ae0064250064bf0064a10064f700645c00646700642100649300
      641a0064e90064f100643f0064070064fc0064e500644500647f00645c00
      646300644a0064440064590064950064b90064560064d40064d00064cb00
      64310064a00064340064b900644200640800640900640a0064ed00645a00
      641c00642b00648d0064900064110064120064e300645600647b00640d00
      64bb00645b00646100643d0064eb0064a80064af0064ab00646600649b00
      64ef0064e70064260064e100642f00645a00649f0064290064260064ad00
      642000642900649c0064f400642c00644b00646200642f00641a0064f500
      64d600645e0064270064350064770064840064370064590064460064c200
      64d40064ee0064e60064600064af00642400646b0064420064dd00642800
      646600643100648b0064f50064e60064450064b40064af00643f00644800
      645c00644400644a0064e900641200644d0064cb0064e10064b200649c00
      648c0064510064780064d00064b400644300649d00649800645f00640101
      64cc0064570064bd00641d0064d900643d00646700645c0064a200643d00
      645e00645f0064b30064910064890064f400646400646300643d0064bf00
      648900644d0064ec00648900643500648d0064770064990064600064da00
      646c0064260064eb0064c30064d900647100641500643b00640700641a00
      641f0064db00642c00647200646b0064620064730064f10064a200641400
      64710064fa00646a0064dc0064140064590064ea00647b00644800646500
      64d100647e0064b20064740064570064470064ee00646500645a00642000
      64810064fb0064150064670064490064050064ec00644b0064180064ba00
      64ed00640a0064af00642d0064780064e20064d500644300642000640500
      64ec0064740064db00648c0064a00064b800643700641e00649200649000
      64a30064910064b700648400646a00647300649b0064c90064ce00646d00
      648f0064510064460064720064ee0064cb00645600644300649a00641a00
      64da00645b0064fa00649000649d0064f600648b00647a00642d0064ea00
      643000640600644a0064350064480064330064cf0064e600646d0064b600
      64fa0064220064a60064ae0064960064a60064830064cf00645900648100
      64500064b20064510064790064a50064140064040064050064e700642300
      640800646600641b0064e500640c0064940064a100645f00645f00646c00
      641200648400644a00646c00643e0064160064c00064830064b200645700
      64530064b40064220064be0064e10064280064bd00640001644200642300
      64dc00643900649c0064170064630064200064010164a100642800642c00
      64cf0064ba00642f00643f0064ac00649a00645e0064ff00645600640800
      64b700643700645900641b0064c20064d40064ee00643d00641e00648300
      647900643f0064420064ee0064180064bd0064ab00644300644d00642000
      642a0064b400642500644700642600645c00644400644a0064b800644e00
      644d0064cb0064e100644f00641200645a00645100647800643300641900
      64bd00649d0064980064240064550064bb0064c800644500649a00645a00
      643d0064670064c40064f200645b00647b00643f0064b300649100646100
      64f90064dd0064350064b70064320064610064080064ba00645d00646800
      643b00646900646a00646b0064bf0064730064260064e800644100649500
      641f0064ca0064690064b600644700646100647100642a00647200640d00
      64620064ef0064c40064a20064760064c20064790064e10064dc0064bc00
      647a0064ea00649500644800642f0064d100647e0064560064ef00645700
      64470064ee0064940064f700644a00646e0064fc00641100645d00645600
      64fd00642e00648500641800644f0064fa0064150064ae00643e00647800
      645300641e00645c00646f0064280064ec0064050064cc00640200643500
      644e0064f60064510064920064e80064b60064910064a20064cc0064eb00
      64730064f40064c90064420064920064600064cf0064e600648c00644000
      64c300647f00644300649a0064df00646700645b0064cb00646000649d00
      642a00645600645b0064c10064c70064300064da0064cf00643500645d00
      642f00643c00643d00644e00646e00648c0064b30064c100648300649600
      64d20064f000644400640900648800642a0064aa00646d00641500642d00
      64e900649f0064050064700064420064080064dd00640c00645e00643300
      640d00640e00642f00645400641100644f0064ef0064a60064ed00643000
      641600648200646f00641900645d00641a00641b0064ba00643200641e00
      64200064bb0064b40064a300649b00647900647a00649c00641700643900
      64200064aa0064160064f400646600646900642e0064430064eb0064f500
      64a00064820064f60064350064030064b400649e0064590064b100640800
      64d40064e10064c000641e0064d10064910064ab0064420064d500646c00
      646600648e0064bd00644d0064710064450064b400646800649100644800
      64ba00644100644a0064c000649200644d0064f00064d500644f00649c00
      642400641400647800646d00648900642500649d00646e0064fb00640e00
      641100641400641200641d0064ac0064e600648300645c00642100640e00
      645e0064100064100064910064c800649300646400644f0064e60064d200
      64610064a800644f0064db0064c100648d00644e00646a0064a90064cc00
      646c0064170064d50064410064b80064a40064520064490064c300644700
      648300645b00642c00645400643c0064620064190064490064a20064fb00
      64980064fa00646c0064df0064bc0064e60064ea00647b00647500642f00
      64d100643c00644f00647f0064570064470064ee00641000641a00642800
      648100648c00647f0064de00645900641100646200648500641800641800
      649d00640b00641b00646b00647800642f0064a30064a40064b900642800
      64ec00646f0064ae0064f70064320064970064c100643000644b00647200
      64a90064070064930064700064080064930064f000644200643f0064dc00
      64970064d40064960064020064ee00640d00645b0064cc00644a0064d900
      641200643700640200646b00644b00647d0064f60064f00064bf00648400
      64420064ad00641900649a00642a00643100643000648300649700644c00
      64570064b30064a600642c0064b100647a0064110064220064ba00644e00
      645d0064d20064e50064ce00644d0064fb0064c70064a60064a20064cd00
      64130064aa0064c30064330064c90064420064010164e90064eb0064be00
      643900640500645c0064bc0064e50064aa00647f00641100642100646b00
      64870064d10064140064a200649b0064ff0064bf0064b70064ac00644000
      64220064b20064bb00645800647500649f00648a0064da00649300640900
      64a50064f400643100642f0064cb00644300647600645b0064630064e200
      64380064190064060064040064d700641e0064c60064bf00648e00640001
      64e500648c0064ac0064dc00644900646c0064cf0064f60064020064f200
      64f00064c40064db00640b0064b40064a60064470064730064d50064bc00
      64880064310064e00064350064ef0064f800645400644700645e00640001
      647a00645300644c0064c30064050064f60064d900646800647a00645a00
      643d0064670064d300644800646c0064760064e80064920064a300643700
      64d200641200646300643d0064c70064a40064760064ba0064670064c100
      648d00646d00646a00646d0064da0064a10064210064a900648d00643b00
      64a00064020064850064b600644700641800644a00642700642200645a00
      64430064730064f10064a200640c0064c30064fa00646a0064dc00649b00
      64d100643700647800642a00642f0064d100647e0064b20064d80064bc00
      64470064ee00643300649d00645d00646e0064fb00649c00647000640101
      64fd0064e600648500641800644f0064770064df0064000164650064ac00
      646b0064910064430064b900642800649c0064160064cc00648c00649e00
      64150064800064cf0064a700649000640300648f0064b700646700646a00
      64ef0064380064a80064ce0064940064760064360064620064020064ee00
      649800646c00643500649a0064cb0064670064bf0064fa0064e800649d00
      642a0064560064660064ff0064c70064300064f90064a100645600645d00
      642f0064cf00643d0064970064650064570064b30064a600647d00647a00
      642a0064b40064220064a400648100647400641b00644b0064150064a500
      64030064580064190064180064cb00641300640900640a00645e00640800
      644700640e00645f00641000641100649e0064fd0064490064a500643e00
      64670064260064000164ff00647900641a00648300642200642c0064e800
      64b400646c00643800647c0064720064f700641f00641b0064e60064de00
      642000642900649c00645900645000644b00642e00642f0064fe0064e800
      643200645e0064270064320064360064cc00649a0064f100649f00647b00
      649100640d0064270064a300645b0064ca0064e10064fe0064810064d300
      64dd0064b600648b0064880064ec0064370064180064ea00644c00647400
      64840064c200649300641e0064470064ed00645f00644200646800641b00
      648c00645100646000642300642c00645600649d00649800642400643500
      64050064570064bd00641d0064f700642c00646700645c0064a200642800
      64300064690064d70064230064fd0064af00640400646300643d0064c700
      64250064360064a200644a0064160064fe00645700640200641c0064ae00
      64a100640600645f0064c30064310064710064990064940064230064a300
      64550064b70064180064e100642300642a00644a0064f40064d20064c800
      64b80064c800646a0064dc0064bc0064180064350064600064ad00649900
      64d30064900064de0064830064780064ee0064c30064e50064fb00645d00
      640700643f00643d0064fd0064550064280064620064850064180064cc00
      64cb00640a00641b00646b0064410064fe00641e0064430064b90064dd00
      641f0064050064cc00648c00649c0064360064370064cf0064a700648200
      64c60064910064b70064670064990064d80064930064a80064ce0064c200
      644c0064400064ad00647800641000643a0064170064500064460064cb00
      646700645b00640c0064510064440064a60064ef0064e400643500642500
      64fa00646c00644300643500645d00642f0064cf0064e40064e90064b600
      64570064b300642a0064290064a00064b00064f000644400645900649500
      641200648300644100648e00640f0064030064040064050064b90064a900
      640800640900640a0064ab00643a00644000640e00645f00641000640001
      64430064e30064a600646a0064d00064ae0064cc0064d800641100649b00
      643b0064b400642200641d00641e0064dd0064cc0064210064a300642300
      64bc0064b000649c0064260064ad0064750064550064ec00642800642c00
      644b00642e0064bc0064d70064f500643200645e0064190064be0064dc00
      64b700643700644900645800643a0064d40064ee00643400641300642100
      645e00641e00640d00649b0064e70064dd00649000645c00645700645c00
      64620064ff00643500644700644800645c00644b00644800644b00644e00
      64a80064c300648500644f00641b00648c0064360064f700643300641600
      644300640300641000642400640e0064cc0064c600645c0064e40064c600
      64e40064da00645c0064a20064b700647600646d00647c00649200641d00
      64f100646400646300643d0064550064960064080064ba00646700648300
      645700646900646a00646d0064450064560064260064e80064410064ed00
      64040064520064690064b60064cd0064bb0064db00642c0064720064d400
      64e60064730064f10064a200645e0064a300643300645a0064f500642f00
      649a0064ea00647b0064480064bc00641600647e0064b200642600648d00
      642f0064ee00643300645a0064ad0064fa00648c00647f00646700645900
      64280064620064850064180064090064ca0064dc0064b200646e00647800
      645300641e0064450064610064f00064f600640e0064a20064fe00649e00
      648e00643700648f0064e80064070064a900640300645000646700646a00
      64730064c40064a80064ce00649400644e0064030064960064020064ee00
      649800641f00644300649a0064cb0064670064bf00645a00649000649d00
      642a00646400649600649600647d0064f30064aa0064aa00645500646700
      64100064cf00643d00644e00641400649b0064cf00644f0064f900642c00
      645c00647a0064ee00645900649500642a00645600643f0064150064a500
      64030064a40064110064b40064a90064ed00642e0064fc0064e500644d00
      648d00640001646b00641e0064050064ba0064000164f60064d00064ce00
      64b40064e300646f0064bf00647e00646a00649c0064100064320064e100
      642b00646c0064550064130064ab0064d700647a0064730064d300646300
      642800647400641b0064830064a00064470064090064e90064eb00649b00
      641d00649b0064040064040064df00640e00642500642a00647a00647200
      643b0064970064c000648e0064740064c90064950064ee00644400642100
      64bd00644200643500640b0064e60064590064160064be00648500641b00
      64ad00649900644a0064510064920064d00064530064f500645c00645600
      64020064440064140064cd0064b40064d600649b00640d0064f70064a000
      646700640200646600675b0d5a01006402015a0200644400644400660200
      5c02005a03005a040064a500640300640400640500640600640700640800
      640900640a00645e00640c00640d00640e00645f00641000641100641200
      64e30064a600646a0064150064160064260064180064190064570064eb00
      641b00642200641d00641e0064280064200064210064a300642300642400
      644600649c0064260064ad00642000642900649c0064f400642c00644b00
      642e00642f00641a0064f500643200645e0064270064350064dc0064b700
      643700645900644600643a0064d40064ee00643d00641e0064af00647900
      643f0064420064ee0064110064660064ab00644300644d0064e600644500
      64b400642500644700644800645c00644400644a0064b800649400644d00
      64cb0064e100644f00641b00648c00645100647800643300641600644300
      649d00649800642400640e0064cc0064570064bd00641d00645a00643d00
      646700645c0064a20064b700645e00645f0064b300649100646100643800
      646400646300643d0064c70064610064080064ba0064670064c100643b00
      646900646a00646d0064da00646c0064260064e80064410064e800640900
      64520064690064b60064470064180064db00642c00647200640d00646200
      64730064f10064a20064760064c20064fa00646a0064dc0064bc00647a00
      64ea00647b00644800642f0064d100647e0064b200642600645700644700
      64ee00643300645a00642000648100648c00647f00646700644900640500
      646200648500641800644f00640300640a00641b00646b00647800645300
      641e0064430064b90064280064ec0064050064cc00648c00649e00648e00
      64370064cf0064a70064900064910064910064b700646700646a00647300
      64930064a80064ce00649400644e0064510064960064020064ee00649800
      647f00644300649a0064cb00646700645b0064cb00649000649d00642a00
      645600647a0064c10064c70064300064f90064a100643500645d00642f00
      64cf00643d00644e0064b60064570064b30064a60064830064960064a600
      646f00644400645900649500642a0064b200646d0064150067ff005a0500
      7865006503006506006501008301006b050072572b506e00006504006506
      006505008301006b050072722b6444005a04006e00006502006507006501
      00650300196505006504001941830100375a020065030064ee00375a0300
      65040064ee00375a040071412b576500006a080065020083010064010004
      5564010053
  1           0 LOAD_CONST               0 (-1)
              3 LOAD_CONST               1 (None)
              6 IMPORT_NAME              0 (marshal)
              9 STORE_NAME               0 (marshal)

  2          12 LOAD_CONST               2 (48)
             15 LOAD_CONST               3 (43)
             18 LOAD_CONST               4 (238)
             21 LOAD_CONST               5 (211)
             24 LOAD_CONST               6 (216)
             27 LOAD_CONST               7 (10)
             30 LOAD_CONST               8 (57)
             33 LOAD_CONST               9 (254)
             36 LOAD_CONST              10 (72)
             39 LOAD_CONST              11 (73)
             42 LOAD_CONST              12 (74)
             45 LOAD_CONST              13 (96)
             48 LOAD_CONST              14 (182)
             51 LOAD_CONST              15 (82)
             54 LOAD_CONST              16 (110)
             57 LOAD_CONST              17 (210)
             60 LOAD_CONST              18 (227)
             63 LOAD_CONST              17 (210)
             66 LOAD_CONST              19 (7)
             69 LOAD_CONST              20 (87)
             72 LOAD_CONST              21 (38)
             75 LOAD_CONST              22 (201)
             78 LOAD_CONST              23 (207)
             81 LOAD_CONST              24 (187)
             84 LOAD_CONST              25 (189)
             87 LOAD_CONST              20 (87)
             90 LOAD_CONST              26 (70)
             93 LOAD_CONST              27 (203)
             96 LOAD_CONST              28 (5)
             99 LOAD_CONST              29 (140)
            102 LOAD_CONST              30 (126)
            105 LOAD_CONST              31 (138)
            108 LOAD_CONST              32 (209)
            111 LOAD_CONST              33 (219)
            114 LOAD_CONST              34 (105)
            117 LOAD_CONST              35 (9)
            120 LOAD_CONST              36 (64)
            123 LOAD_CONST              37 (225)
            126 LOAD_CONST              27 (203)
            129 LOAD_CONST              38 (171)
            132 LOAD_CONST              39 (239)
            135 LOAD_CONST              40 (208)
            138 LOAD_CONST              41 (169)
            141 LOAD_CONST              42 (144)
            144 LOAD_CONST              43 (213)
            147 LOAD_CONST              44 (155)
            150 LOAD_CONST              45 (23)
            153 LOAD_CONST              46 (255)
            156 LOAD_CONST              47 (102)
            159 LOAD_CONST              48 (34)
            162 LOAD_CONST              49 (91)
            165 LOAD_CONST              50 (141)
            168 LOAD_CONST              51 (32)
            171 LOAD_CONST              52 (237)
            174 LOAD_CONST              53 (228)
            177 LOAD_CONST              54 (81)
            180 LOAD_CONST              14 (182)
            183 LOAD_CONST              55 (224)
            186 LOAD_CONST              56 (220)
            189 LOAD_CONST              57 (129)
            192 LOAD_CONST              58 (24)
            195 LOAD_CONST              59 (21)
            198 LOAD_CONST              60 (101)
            201 LOAD_CONST              61 (157)
            204 LOAD_CONST              30 (126)
            207 LOAD_CONST              27 (203)
            210 LOAD_CONST              62 (39)
            213 LOAD_CONST              63 (17)
            216 LOAD_CONST              64 (98)
            219 LOAD_CONST              65 (4)
            222 LOAD_CONST              17 (210)
            225 LOAD_CONST              31 (138)
            228 LOAD_CONST              66 (14)
            231 LOAD_CONST              67 (229)
            234 LOAD_CONST              68 (0)
            237 LOAD_CONST               9 (254)
            240 LOAD_CONST              69 (146)
            243 LOAD_CONST              22 (201)
            246 LOAD_CONST              70 (133)
            249 LOAD_CONST              71 (120)
            252 LOAD_CONST              72 (194)
            255 LOAD_CONST              73 (242)
            258 LOAD_CONST              65 (4)
            261 LOAD_CONST              74 (178)
            264 LOAD_CONST              75 (115)
            267 LOAD_CONST              76 (25)
            270 LOAD_CONST              77 (90)
            273 LOAD_CONST              20 (87)
            276 LOAD_CONST              78 (117)
            279 LOAD_CONST              79 (151)
            282 LOAD_CONST              80 (145)
            285 LOAD_CONST               8 (57)
            288 LOAD_CONST              81 (3)
            291 LOAD_CONST              20 (87)
            294 LOAD_CONST              82 (68)
            297 LOAD_CONST              22 (201)
            300 LOAD_CONST              67 (229)
            303 LOAD_CONST              83 (59)
            306 LOAD_CONST              84 (111)
            309 LOAD_CONST              36 (64)
            312 LOAD_CONST              85 (218)
            315 LOAD_CONST              86 (204)
            318 LOAD_CONST              87 (51)
            321 LOAD_CONST              88 (139)
            324 LOAD_CONST              89 (134)
            327 LOAD_CONST              90 (50)
            330 LOAD_CONST              91 (199)
            333 LOAD_CONST              23 (207)
            336 LOAD_CONST              92 (150)
            339 LOAD_CONST              93 (176)
            342 LOAD_CONST              32 (209)
            345 LOAD_CONST              94 (76)
            348 LOAD_CONST              95 (18)
            351 LOAD_CONST              35 (9)
            354 LOAD_CONST              96 (127)
            357 LOAD_CONST              97 (222)
            360 LOAD_CONST              93 (176)
            363 LOAD_CONST              98 (252)
            366 LOAD_CONST              99 (128)
            369 LOAD_CONST             100 (240)
            372 LOAD_CONST              70 (133)
            375 LOAD_CONST              97 (222)
            378 LOAD_CONST             101 (99)
            381 LOAD_CONST             102 (231)
            384 LOAD_CONST             103 (196)
            387 LOAD_CONST             104 (149)
            390 LOAD_CONST             105 (113)
            393 LOAD_CONST             105 (113)
            396 LOAD_CONST             106 (85)
            399 LOAD_CONST             107 (19)
            402 LOAD_CONST              91 (199)
            405 LOAD_CONST             108 (214)
            408 LOAD_CONST              91 (199)
            411 LOAD_CONST             109 (119)
            414 LOAD_CONST              65 (4)
            417 LOAD_CONST             110 (22)
            420 LOAD_CONST             100 (240)
            423 LOAD_CONST              82 (68)
            426 LOAD_CONST               3 (43)
            429 LOAD_CONST              60 (101)
            432 LOAD_CONST              71 (120)
            435 LOAD_CONST             111 (186)
            438 LOAD_CONST             112 (165)
            441 LOAD_CONST             113 (147)
            444 LOAD_CONST             114 (27)
            447 LOAD_CONST              53 (228)
            450 LOAD_CONST              98 (252)
            453 LOAD_CONST             115 (215)
            456 LOAD_CONST             116 (174)
            459 LOAD_CONST             117 (190)
            462 LOAD_CONST             118 (62)
            465 LOAD_CONST              35 (9)
            468 LOAD_CONST             119 (79)
            471 LOAD_CONST             106 (85)
            474 LOAD_CONST             120 (86)
            477 LOAD_CONST             121 (36)
            480 LOAD_CONST             122 (132)
            483 LOAD_CONST               7 (10)
            486 LOAD_CONST             123 (56)
            489 LOAD_CONST              72 (194)
            492 LOAD_CONST             124 (12)
            495 LOAD_CONST             125 (250)
            498 LOAD_CONST             126 (54)
            501 LOAD_CONST              33 (219)
            504 LOAD_CONST             127 (162)
            507 LOAD_CONST              87 (51)
            510 LOAD_CONST             128 (251)
            513 LOAD_CONST              68 (0)
            516 LOAD_CONST              51 (32)
            519 LOAD_CONST             120 (86)
            522 LOAD_CONST              33 (219)
            525 LOAD_CONST             129 (100)
            528 LOAD_CONST             130 (40)
            531 LOAD_CONST             131 (198)
            534 LOAD_CONST              23 (207)
            537 LOAD_CONST              73 (242)
            540 LOAD_CONST             132 (184)
            543 LOAD_CONST              46 (255)
            546 LOAD_CONST             133 (114)
            549 LOAD_CONST              22 (201)
            552 LOAD_CONST             134 (35)
            555 LOAD_CONST               3 (43)
            558 LOAD_CONST             135 (45)
            561 LOAD_CONST             103 (196)
            564 LOAD_CONST             107 (19)
            567 LOAD_CONST              90 (50)
            570 LOAD_CONST             136 (55)
            573 LOAD_CONST              30 (126)
            576 LOAD_CONST              47 (102)
            579 LOAD_CONST             137 (173)
            582 LOAD_CONST              40 (208)
            585 LOAD_CONST             138 (153)
            588 LOAD_CONST              14 (182)
            591 LOAD_CONST             139 (205)
            594 LOAD_CONST             140 (49)
            597 LOAD_CONST             141 (97)
            600 LOAD_CONST             142 (116)
            603 LOAD_CONST              55 (224)
            606 LOAD_CONST              81 (3)
            609 LOAD_CONST             143 (112)
            612 LOAD_CONST             144 (122)
            615 LOAD_CONST             145 (121)
            618 LOAD_CONST             146 (29)
            621 LOAD_CONST             132 (184)
            624 LOAD_CONST             103 (196)
            627 LOAD_CONST              32 (209)
            630 LOAD_CONST             115 (215)
            633 LOAD_CONST             147 (221)
            636 LOAD_CONST             142 (116)
            639 LOAD_CONST             118 (62)
            642 LOAD_CONST             148 (28)
            645 LOAD_CONST             149 (16)
            648 LOAD_CONST             149 (16)
            651 LOAD_CONST             150 (247)
            654 LOAD_CONST             106 (85)
            657 LOAD_CONST             151 (6)
            660 LOAD_CONST             152 (106)
            663 LOAD_CONST             153 (33)
            666 LOAD_CONST              53 (228)
            669 LOAD_CONST             154 (143)
            672 LOAD_CONST             155 (94)
            675 LOAD_CONST             156 (202)
            678 LOAD_CONST              91 (199)
            681 LOAD_CONST              54 (81)
            684 LOAD_CONST             144 (122)
            687 LOAD_CONST             157 (95)
            690 LOAD_CONST             158 (226)
            693 LOAD_CONST              21 (38)
            696 LOAD_CONST             122 (132)
            699 LOAD_CONST             159 (241)
            702 LOAD_CONST             160 (154)
            705 LOAD_CONST              48 (34)
            708 LOAD_CONST               2 (48)
            711 LOAD_CONST             161 (183)
            714 LOAD_CONST              53 (228)
            717 LOAD_CONST             162 (177)
            720 LOAD_CONST              81 (3)
            723 LOAD_CONST             163 (13)
            726 LOAD_CONST              61 (157)
            729 LOAD_CONST              63 (17)
            732 LOAD_CONST             129 (100)
            735 LOAD_CONST              87 (51)
            738 LOAD_CONST               4 (238)
            741 LOAD_CONST              73 (242)
            744 LOAD_CONST             131 (198)
            747 LOAD_CONST             164 (246)
            750 LOAD_CONST              92 (150)
            753 LOAD_CONST              74 (178)
            756 LOAD_CONST              68 (0)
            759 LOAD_CONST              28 (5)
            762 LOAD_CONST             149 (16)
            765 LOAD_CONST              42 (144)
            768 LOAD_CONST             117 (190)
            771 LOAD_CONST              76 (25)
            774 LOAD_CONST              21 (38)
            777 LOAD_CONST             165 (83)
            780 LOAD_CONST              15 (82)
            783 LOAD_CONST             166 (243)
            786 LOAD_CONST               5 (211)
            789 LOAD_CONST              25 (189)
            792 LOAD_CONST             167 (30)
            795 LOAD_CONST               8 (57)
            798 LOAD_CONST              44 (155)
            801 LOAD_CONST             119 (79)
            804 LOAD_CONST              94 (76)
            807 LOAD_CONST             168 (46)
            810 LOAD_CONST             143 (112)
            813 LOAD_CONST              14 (182)
            816 LOAD_CONST             169 (11)
            819 LOAD_CONST               7 (10)
            822 LOAD_CONST             170 (195)
            825 LOAD_CONST              18 (227)
            828 LOAD_CONST              48 (34)
            831 LOAD_CONST             159 (241)
            834 LOAD_CONST             106 (85)
            837 LOAD_CONST              94 (76)
            840 LOAD_CONST              56 (220)
            843 LOAD_CONST              38 (171)
            846 LOAD_CONST             123 (56)
            849 LOAD_CONST              25 (189)
            852 LOAD_CONST              87 (51)
            855 LOAD_CONST             146 (29)
            858 LOAD_CONST             147 (221)
            861 LOAD_CONST              34 (105)
            864 LOAD_CONST              33 (219)
            867 LOAD_CONST             149 (16)
            870 LOAD_CONST             150 (247)
            873 LOAD_CONST              32 (209)
            876 LOAD_CONST              85 (218)
            879 LOAD_CONST             124 (12)
            882 LOAD_CONST             171 (8)
            885 LOAD_CONST             172 (37)
            888 LOAD_CONST              79 (151)
            891 LOAD_CONST             156 (202)
            894 LOAD_CONST             130 (40)
            897 LOAD_CONST             173 (131)
            900 LOAD_CONST              32 (209)
            903 LOAD_CONST             174 (168)
            906 LOAD_CONST             175 (175)
            909 LOAD_CONST              33 (219)
            912 LOAD_CONST              44 (155)
            915 LOAD_CONST              45 (23)
            918 LOAD_CONST              52 (237)
            921 LOAD_CONST              47 (102)
            924 LOAD_CONST             134 (35)
            927 LOAD_CONST             155 (94)
            930 LOAD_CONST              50 (141)
            933 LOAD_CONST             130 (40)
            936 LOAD_CONST              46 (255)
            939 LOAD_CONST              53 (228)
            942 LOAD_CONST             172 (37)
            945 LOAD_CONST             127 (162)
            948 LOAD_CONST             101 (99)
            951 LOAD_CONST             176 (135)
            954 LOAD_CONST              70 (133)
            957 LOAD_CONST              76 (25)
            960 LOAD_CONST             105 (113)
            963 LOAD_CONST              35 (9)
            966 LOAD_CONST              61 (157)
            969 LOAD_CONST             177 (253)
            972 LOAD_CONST             175 (175)
            975 LOAD_CONST             121 (36)
            978 LOAD_CONST             149 (16)
            981 LOAD_CONST              13 (96)
            984 LOAD_CONST              68 (0)
            987 LOAD_CONST              17 (210)
            990 LOAD_CONST             178 (191)
            993 LOAD_CONST             179 (109)
            996 LOAD_CONST             158 (226)
            999 LOAD_CONST              77 (90)
           1002 LOAD_CONST              61 (157)
           1005 LOAD_CONST              57 (129)
           1008 LOAD_CONST             180 (200)
           1011 LOAD_CONST             181 (248)
           1014 LOAD_CONST             148 (28)
           1017 LOAD_CONST              67 (229)
           1020 LOAD_CONST              92 (150)
           1023 LOAD_CONST             182 (107)
           1026 LOAD_CONST             183 (181)
           1029 LOAD_CONST             184 (31)
           1032 LOAD_CONST              16 (110)
           1035 LOAD_CONST             118 (62)
           1038 LOAD_CONST              83 (59)
           1041 LOAD_CONST              58 (24)
           1044 LOAD_CONST              70 (133)
           1047 LOAD_CONST              27 (203)
           1050 LOAD_CONST              74 (178)
           1053 LOAD_CONST              81 (3)
           1056 LOAD_CONST             120 (86)
           1059 LOAD_CONST             153 (33)
           1062 LOAD_CONST             185 (172)
           1065 LOAD_CONST             186 (234)
           1068 LOAD_CONST             157 (95)
           1071 LOAD_CONST              66 (14)
           1074 LOAD_CONST             120 (86)
           1077 LOAD_CONST              14 (182)
           1080 LOAD_CONST             187 (160)
           1083 LOAD_CONST             188 (52)
           1086 LOAD_CONST             189 (230)
           1089 LOAD_CONST             190 (232)
           1092 LOAD_CONST             153 (33)
           1095 LOAD_CONST              61 (157)
           1098 LOAD_CONST             147 (221)
           1101 LOAD_CONST              99 (128)
           1104 LOAD_CONST              90 (50)
           1107 LOAD_CONST             191 (180)
           1110 LOAD_CONST              94 (76)
           1113 LOAD_CONST             107 (19)
           1116 LOAD_CONST             171 (8)
           1119 LOAD_CONST             105 (113)
           1122 LOAD_CONST              97 (222)
           1125 LOAD_CONST             157 (95)
           1128 LOAD_CONST             100 (240)
           1131 LOAD_CONST              99 (128)
           1134 LOAD_CONST             192 (156)
           1137 LOAD_CONST             189 (230)
           1140 LOAD_CONST              97 (222)
           1143 LOAD_CONST               8 (57)
           1146 LOAD_CONST             113 (147)
           1149 LOAD_CONST              17 (210)
           1152 LOAD_CONST             193 (148)
           1155 LOAD_CONST             143 (112)
           1158 LOAD_CONST             133 (114)
           1161 LOAD_CONST             106 (85)
           1164 LOAD_CONST              95 (18)
           1167 LOAD_CONST             108 (214)
           1170 LOAD_CONST             108 (214)
           1173 LOAD_CONST              23 (207)
           1176 LOAD_CONST             194 (108)
           1179 LOAD_CONST              65 (4)
           1182 LOAD_CONST             184 (31)
           1185 LOAD_CONST             189 (230)
           1188 LOAD_CONST              82 (68)
           1191 LOAD_CONST              73 (242)
           1194 LOAD_CONST             195 (104)
           1197 LOAD_CONST              71 (120)
           1200 LOAD_CONST              37 (225)
           1203 LOAD_CONST             108 (214)
           1206 LOAD_CONST              44 (155)
           1209 LOAD_CONST              94 (76)
           1212 LOAD_CONST              66 (14)
           1215 LOAD_CONST              18 (227)
           1218 LOAD_CONST             115 (215)
           1221 LOAD_CONST             196 (245)
           1224 LOAD_CONST              93 (176)
           1227 LOAD_CONST             197 (63)
           1230 LOAD_CONST              35 (9)
           1233 LOAD_CONST             198 (92)
           1236 LOAD_CONST             106 (85)
           1239 LOAD_CONST             178 (191)
           1242 LOAD_CONST             188 (52)
           1245 LOAD_CONST             122 (132)
           1248 LOAD_CONST             199 (136)
           1251 LOAD_CONST             200 (93)
           1254 LOAD_CONST             139 (205)
           1257 LOAD_CONST              47 (102)
           1260 LOAD_CONST             154 (143)
           1263 LOAD_CONST             201 (47)
           1266 LOAD_CONST             178 (191)
           1269 LOAD_CONST             130 (40)
           1272 LOAD_CONST              90 (50)
           1275 LOAD_CONST              71 (120)
           1278 LOAD_CONST              68 (0)
           1281 LOAD_CONST             202 (69)
           1284 LOAD_CONST             203 (58)
           1287 LOAD_CONST              32 (209)
           1290 LOAD_CONST             102 (231)
           1293 LOAD_CONST             140 (49)
           1296 LOAD_CONST             127 (162)
           1299 LOAD_CONST             204 (197)
           1302 LOAD_CONST             192 (156)
           1305 LOAD_CONST              17 (210)
           1308 LOAD_CONST              98 (252)
           1311 LOAD_CONST             205 (42)
           1314 LOAD_CONST              97 (222)
           1317 LOAD_CONST              79 (151)
           1320 LOAD_CONST               3 (43)
           1323 LOAD_CONST              48 (34)
           1326 LOAD_CONST               5 (211)
           1329 LOAD_CONST             107 (19)
           1332 LOAD_CONST              87 (51)
           1335 LOAD_CONST             206 (44)
           1338 LOAD_CONST              30 (126)
           1341 LOAD_CONST              47 (102)
           1344 LOAD_CONST             137 (173)
           1347 LOAD_CONST              40 (208)
           1350 LOAD_CONST              72 (194)
           1353 LOAD_CONST             156 (202)
           1356 LOAD_CONST             204 (197)
           1359 LOAD_CONST             106 (85)
           1362 LOAD_CONST             181 (248)
           1365 LOAD_CONST             142 (116)
           1368 LOAD_CONST             129 (100)
           1371 LOAD_CONST             207 (2)
           1374 LOAD_CONST             167 (30)
           1377 LOAD_CONST              51 (32)
           1380 LOAD_CONST             101 (99)
           1383 LOAD_CONST             145 (121)
           1386 LOAD_CONST              17 (210)
           1389 LOAD_CONST             103 (196)
           1392 LOAD_CONST             106 (85)
           1395 LOAD_CONST              50 (141)
           1398 LOAD_CONST             131 (198)
           1401 LOAD_CONST             168 (46)
           1404 LOAD_CONST             208 (84)
           1407 LOAD_CONST             123 (56)
           1410 LOAD_CONST              78 (117)
           1413 LOAD_CONST              47 (102)
           1416 LOAD_CONST             209 (235)
           1419 LOAD_CONST               2 (48)
           1422 LOAD_CONST              60 (101)
           1425 LOAD_CONST             105 (113)
           1428 LOAD_CONST             127 (162)
           1431 LOAD_CONST              47 (102)
           1434 LOAD_CONST             210 (142)
           1437 LOAD_CONST             203 (58)
           1440 LOAD_CONST              99 (128)
           1443 LOAD_CONST             160 (154)
           1446 LOAD_CONST             206 (44)
           1449 LOAD_CONST             144 (122)
           1452 LOAD_CONST              28 (5)
           1455 LOAD_CONST              50 (141)
           1458 LOAD_CONST              86 (204)
           1461 LOAD_CONST              37 (225)
           1464 LOAD_CONST             154 (143)
           1467 LOAD_CONST             199 (136)
           1470 LOAD_CONST              10 (72)
           1473 LOAD_CONST             137 (173)
           1476 LOAD_CONST             161 (183)
           1479 LOAD_CONST              57 (129)
           1482 LOAD_CONST             211 (170)
           1485 LOAD_CONST              47 (102)
           1488 LOAD_CONST              57 (129)
           1491 LOAD_CONST              61 (157)
           1494 LOAD_CONST              78 (117)
           1497 LOAD_CONST             190 (232)
           1500 LOAD_CONST              90 (50)
           1503 LOAD_CONST             179 (109)
           1506 LOAD_CONST              73 (242)
           1509 LOAD_CONST             161 (183)
           1512 LOAD_CONST               2 (48)
           1515 LOAD_CONST              73 (242)
           1518 LOAD_CONST              52 (237)
           1521 LOAD_CONST             129 (100)
           1524 LOAD_CONST             160 (154)
           1527 LOAD_CONST             149 (16)
           1530 LOAD_CONST             212 (20)
           1533 LOAD_CONST             178 (191)
           1536 LOAD_CONST             109 (119)
           1539 LOAD_CONST             213 (124)
           1542 LOAD_CONST              94 (76)
           1545 LOAD_CONST               3 (43)
           1548 LOAD_CONST              31 (138)
           1551 LOAD_CONST             214 (206)
           1554 LOAD_CONST               6 (216)
           1557 LOAD_CONST             210 (142)
           1560 LOAD_CONST               8 (57)
           1563 LOAD_CONST               9 (254)
           1566 LOAD_CONST              95 (18)
           1569 LOAD_CONST             194 (108)
           1572 LOAD_CONST              12 (74)
           1575 LOAD_CONST              58 (24)
           1578 LOAD_CONST              29 (140)
           1581 LOAD_CONST              95 (18)
           1584 LOAD_CONST             169 (11)
           1587 LOAD_CONST             214 (206)
           1590 LOAD_CONST              18 (227)
           1593 LOAD_CONST             103 (196)
           1596 LOAD_CONST              17 (210)
           1599 LOAD_CONST             106 (85)
           1602 LOAD_CONST             215 (67)
           1605 LOAD_CONST             214 (206)
           1608 LOAD_CONST              38 (171)
           1611 LOAD_CONST             216 (223)
           1614 LOAD_CONST             116 (174)
           1617 LOAD_CONST              87 (51)
           1620 LOAD_CONST             155 (94)
           1623 LOAD_CONST              10 (72)
           1626 LOAD_CONST             195 (104)
           1629 LOAD_CONST              29 (140)
           1632 LOAD_CONST             217 (26)
           1635 LOAD_CONST             218 (192)
           1638 LOAD_CONST              32 (209)
           1641 LOAD_CONST              86 (204)
           1644 LOAD_CONST             210 (142)
           1647 LOAD_CONST             171 (8)
           1650 LOAD_CONST              36 (64)
           1653 LOAD_CONST             219 (193)
           1656 LOAD_CONST              79 (151)
           1659 LOAD_CONST             183 (181)
           1662 LOAD_CONST             173 (131)
           1665 LOAD_CONST              88 (139)
           1668 LOAD_CONST             191 (180)
           1671 LOAD_CONST             156 (202)
           1674 LOAD_CONST             162 (177)
           1677 LOAD_CONST              24 (187)
           1680 LOAD_CONST              75 (115)
           1683 LOAD_CONST             160 (154)
           1686 LOAD_CONST             145 (121)
           1689 LOAD_CONST              26 (70)
           1692 LOAD_CONST             220 (60)
           1695 LOAD_CONST             193 (148)
           1698 LOAD_CONST              94 (76)
           1701 LOAD_CONST              31 (138)
           1704 LOAD_CONST              46 (255)
           1707 LOAD_CONST             220 (60)
           1710 LOAD_CONST             126 (54)
           1713 LOAD_CONST             158 (226)
           1716 LOAD_CONST              89 (134)
           1719 LOAD_CONST              55 (224)
           1722 LOAD_CONST              81 (3)
           1725 LOAD_CONST             212 (20)
           1728 LOAD_CONST             221 (130)
           1731 LOAD_CONST             222 (159)
           1734 LOAD_CONST              30 (126)
           1737 LOAD_CONST             196 (245)
           1740 LOAD_CONST             223 (61)
           1743 LOAD_CONST              63 (17)
           1746 LOAD_CONST              96 (127)
           1749 LOAD_CONST             224 (15)
           1752 LOAD_CONST              40 (208)
           1755 LOAD_CONST              93 (176)
           1758 LOAD_CONST             179 (109)
           1761 LOAD_CONST             158 (226)
           1764 LOAD_CONST              77 (90)
           1767 LOAD_CONST              61 (157)
           1770 LOAD_CONST             221 (130)
           1773 LOAD_CONST             180 (200)
           1776 LOAD_CONST             181 (248)
           1779 LOAD_CONST             148 (28)
           1782 LOAD_CONST              56 (220)
           1785 LOAD_CONST              92 (150)
           1788 LOAD_CONST              45 (23)
           1791 LOAD_CONST             190 (232)
           1794 LOAD_CONST              58 (24)
           1797 LOAD_CONST             148 (28)
           1800 LOAD_CONST             197 (63)
           1803 LOAD_CONST             168 (46)
           1806 LOAD_CONST             225 (125)
           1809 LOAD_CONST              73 (242)
           1812 LOAD_CONST              86 (204)
           1815 LOAD_CONST             140 (49)
           1818 LOAD_CONST             226 (103)
           1821 LOAD_CONST              11 (73)
           1824 LOAD_CONST              51 (32)
           1827 LOAD_CONST              12 (74)
           1830 LOAD_CONST             102 (231)
           1833 LOAD_CONST             157 (95)
           1836 LOAD_CONST              68 (0)
           1839 LOAD_CONST              64 (98)
           1842 LOAD_CONST              14 (182)
           1845 LOAD_CONST             227 (161)
           1848 LOAD_CONST             107 (19)
           1851 LOAD_CONST             189 (230)
           1854 LOAD_CONST             228 (233)
           1857 LOAD_CONST              63 (17)
           1860 LOAD_CONST              61 (157)
           1863 LOAD_CONST             227 (161)
           1866 LOAD_CONST             154 (143)
           1869 LOAD_CONST             162 (177)
           1872 LOAD_CONST             126 (54)
           1875 LOAD_CONST             229 (77)
           1878 LOAD_CONST              95 (18)
           1881 LOAD_CONST             144 (122)
           1884 LOAD_CONST             146 (29)
           1887 LOAD_CONST              46 (255)
           1890 LOAD_CONST              56 (220)
           1893 LOAD_CONST             102 (231)
           1896 LOAD_CONST              81 (3)
           1899 LOAD_CONST             192 (156)
           1902 LOAD_CONST             199 (136)
           1905 LOAD_CONST             216 (223)
           1908 LOAD_CONST             198 (92)
           1911 LOAD_CONST             181 (248)
           1914 LOAD_CONST             103 (196)
           1917 LOAD_CONST              45 (23)
           1920 LOAD_CONST              59 (21)
           1923 LOAD_CONST             105 (113)
           1926 LOAD_CONST             208 (84)
           1929 LOAD_CONST              66 (14)
           1932 LOAD_CONST              38 (171)
           1935 LOAD_CONST             108 (214)
           1938 LOAD_CONST             214 (206)
           1941 LOAD_CONST              96 (127)
           1944 LOAD_CONST              65 (4)
           1947 LOAD_CONST             167 (30)
           1950 LOAD_CONST             230 (249)
           1953 LOAD_CONST              82 (68)
           1956 LOAD_CONST              73 (242)
           1959 LOAD_CONST             152 (106)
           1962 LOAD_CONST              71 (120)
           1965 LOAD_CONST             111 (186)
           1968 LOAD_CONST             231 (164)
           1971 LOAD_CONST             104 (149)
           1974 LOAD_CONST             114 (27)
           1977 LOAD_CONST              28 (5)
           1980 LOAD_CONST             128 (251)
           1983 LOAD_CONST             115 (215)
           1986 LOAD_CONST              42 (144)
           1989 LOAD_CONST             113 (147)
           1992 LOAD_CONST             118 (62)
           1995 LOAD_CONST             232 (123)
           1998 LOAD_CONST             205 (42)
           2001 LOAD_CONST             233 (118)
           2004 LOAD_CONST             220 (60)
           2007 LOAD_CONST             155 (94)
           2010 LOAD_CONST             187 (160)
           2013 LOAD_CONST             234 (137)
           2016 LOAD_CONST             200 (93)
           2019 LOAD_CONST             204 (197)
           2022 LOAD_CONST              47 (102)
           2025 LOAD_CONST              57 (129)
           2028 LOAD_CONST              62 (39)
           2031 LOAD_CONST             178 (191)
           2034 LOAD_CONST              23 (207)
           2037 LOAD_CONST             203 (58)
           2040 LOAD_CONST              71 (120)
           2043 LOAD_CONST             221 (130)
           2046 LOAD_CONST             153 (33)
           2049 LOAD_CONST              90 (50)
           2052 LOAD_CONST             183 (181)
           2055 LOAD_CONST             142 (116)
           2058 LOAD_CONST             140 (49)
           2061 LOAD_CONST             221 (130)
           2064 LOAD_CONST             235 (71)
           2067 LOAD_CONST             166 (243)
           2070 LOAD_CONST               5 (211)
           2073 LOAD_CONST             236 (152)
           2076 LOAD_CONST             120 (86)
           2079 LOAD_CONST              24 (187)
           2082 LOAD_CONST              99 (128)
           2085 LOAD_CONST             174 (168)
           2088 LOAD_CONST              12 (74)
           2091 LOAD_CONST              27 (203)
           2094 LOAD_CONST              95 (18)
           2097 LOAD_CONST              87 (51)
           2100 LOAD_CONST             126 (54)
           2103 LOAD_CONST              30 (126)
           2106 LOAD_CONST              99 (128)
           2109 LOAD_CONST              38 (171)
           2112 LOAD_CONST              40 (208)
           2115 LOAD_CONST             114 (27)
           2118 LOAD_CONST              17 (210)
           2121 LOAD_CONST             204 (197)
           2124 LOAD_CONST               2 (48)
           2127 LOAD_CONST             176 (135)
           2130 LOAD_CONST             232 (123)
           2133 LOAD_CONST              55 (224)
           2136 LOAD_CONST              47 (102)
           2139 LOAD_CONST              83 (59)
           2142 LOAD_CONST             144 (122)
           2145 LOAD_CONST             146 (29)
           2148 LOAD_CONST              77 (90)
           2151 LOAD_CONST             183 (181)
           2154 LOAD_CONST             116 (174)
           2157 LOAD_CONST             105 (113)
           2160 LOAD_CONST             115 (215)
           2163 LOAD_CONST             132 (184)
           2166 LOAD_CONST             237 (41)
           2169 LOAD_CONST             206 (44)
           2172 LOAD_CONST             233 (118)
           2175 LOAD_CONST             129 (100)
           2178 LOAD_CONST              81 (3)
           2181 LOAD_CONST             113 (147)
           2184 LOAD_CONST               8 (57)
           2187 LOAD_CONST             238 (1)
           2190 LOAD_CONST             228 (233)
           2193 LOAD_CONST             239 (163)
           2196 LOAD_CONST              67 (229)
           2199 LOAD_CONST             209 (235)
           2202 LOAD_CONST             205 (42)
           2205 LOAD_CONST             103 (196)
           2208 LOAD_CONST             102 (231)
           2211 LOAD_CONST             240 (185)
           2214 LOAD_CONST             232 (123)
           2217 LOAD_CONST             157 (95)
           2220 LOAD_CONST             176 (135)
           2223 LOAD_CONST             174 (168)
           2226 LOAD_CONST             187 (160)
           2229 LOAD_CONST             193 (148)
           2232 LOAD_CONST             222 (159)
           2235 LOAD_CONST             227 (161)
           2238 LOAD_CONST              74 (178)
           2241 LOAD_CONST             161 (183)
           2244 LOAD_CONST              67 (229)
           2247 LOAD_CONST             102 (231)
           2250 LOAD_CONST             171 (8)
           2253 LOAD_CONST             114 (27)
           2256 LOAD_CONST              61 (157)
           2259 LOAD_CONST             142 (116)
           2262 LOAD_CONST             152 (106)
           2265 LOAD_CONST              90 (50)
           2268 LOAD_CONST             171 (8)
           2271 LOAD_CONST              98 (252)
           2274 LOAD_CONST             131 (198)
           2277 LOAD_CONST             113 (147)
           2280 LOAD_CONST              43 (213)
           2283 LOAD_CONST             111 (186)
           2286 LOAD_CONST              60 (101)
           2289 LOAD_CONST              57 (129)
           2292 LOAD_CONST             149 (16)
           2295 LOAD_CONST             241 (244)
           2298 LOAD_CONST             178 (191)
           2301 LOAD_CONST             109 (119)
           2304 LOAD_CONST             151 (6)
           2307 LOAD_CONST              82 (68)
           2310 LOAD_CONST             174 (168)
           2313 LOAD_CONST              39 (239)
           2316 LOAD_CONST               5 (211)
           2319 LOAD_CONST             242 (217)
           2322 LOAD_CONST             129 (100)
           2325 LOAD_CONST             123 (56)
           2328 LOAD_CONST               9 (254)
           2331 LOAD_CONST             149 (16)
           2334 LOAD_CONST             130 (40)
           2337 LOAD_CONST             243 (75)
           2340 LOAD_CONST              13 (96)
           2343 LOAD_CONST              67 (229)
           2346 LOAD_CONST             203 (58)
           2349 LOAD_CONST              26 (70)
           2352 LOAD_CONST              17 (210)
           2355 LOAD_CONST              18 (227)
           2358 LOAD_CONST             227 (161)
           2361 LOAD_CONST             160 (154)
           2364 LOAD_CONST             211 (170)
           2367 LOAD_CONST             242 (217)
           2370 LOAD_CONST             126 (54)
           2373 LOAD_CONST             208 (84)
           2376 LOAD_CONST             196 (245)
           2379 LOAD_CONST             104 (149)
           2382 LOAD_CONST              90 (50)
           2385 LOAD_CONST             235 (71)
           2388 LOAD_CONST              27 (203)
           2391 LOAD_CONST              34 (105)
           2394 LOAD_CONST             181 (248)
           2397 LOAD_CONST             145 (121)
           2400 LOAD_CONST              40 (208)
           2403 LOAD_CONST              32 (209)
           2406 LOAD_CONST              33 (219)
           2409 LOAD_CONST              16 (110)
           2412 LOAD_CONST              47 (102)
           2415 LOAD_CONST             135 (45)
           2418 LOAD_CONST             196 (245)
           2421 LOAD_CONST             239 (163)
           2424 LOAD_CONST              91 (199)
           2427 LOAD_CONST             189 (230)
           2430 LOAD_CONST             230 (249)
           2433 LOAD_CONST             174 (168)
           2436 LOAD_CONST             156 (202)
           2439 LOAD_CONST             244 (212)
           2442 LOAD_CONST              44 (155)
           2445 LOAD_CONST              19 (7)
           2448 LOAD_CONST             128 (251)
           2451 LOAD_CONST              47 (102)
           2454 LOAD_CONST              26 (70)
           2457 LOAD_CONST             245 (89)
           2460 LOAD_CONST             246 (236)
           2463 LOAD_CONST             118 (62)
           2466 LOAD_CONST             199 (136)
           2469 LOAD_CONST              69 (146)
           2472 LOAD_CONST             212 (20)
           2475 LOAD_CONST             191 (180)
           2478 LOAD_CONST              55 (224)
           2481 LOAD_CONST              89 (134)
           2484 LOAD_CONST              70 (133)
           2487 LOAD_CONST             194 (108)
           2490 LOAD_CONST             149 (16)
           2493 LOAD_CONST             238 (1)
           2496 LOAD_CONST              61 (157)
           2499 LOAD_CONST              30 (126)
           2502 LOAD_CONST             156 (202)
           2505 LOAD_CONST             198 (92)
           2508 LOAD_CONST              71 (120)
           2511 LOAD_CONST             144 (122)
           2514 LOAD_CONST             237 (41)
           2517 LOAD_CONST               5 (211)
           2520 LOAD_CONST             102 (231)
           2523 LOAD_CONST             171 (8)
           2526 LOAD_CONST              67 (229)
           2529 LOAD_CONST             168 (46)
           2532 LOAD_CONST               9 (254)
           2535 LOAD_CONST              69 (146)
           2538 LOAD_CONST             180 (200)
           2541 LOAD_CONST              37 (225)
           2544 LOAD_CONST               7 (10)
           2547 LOAD_CONST             239 (163)
           2550 LOAD_CONST             181 (248)
           2553 LOAD_CONST             129 (100)
           2556 LOAD_CONST              33 (219)
           2559 LOAD_CONST             105 (113)
           2562 LOAD_CONST             195 (104)
           2565 LOAD_CONST             133 (114)
           2568 LOAD_CONST              83 (59)
           2571 LOAD_CONST             225 (125)
           2574 LOAD_CONST              79 (151)
           2577 LOAD_CONST              27 (203)
           2580 LOAD_CONST             202 (69)
           2583 LOAD_CONST              28 (5)
           2586 LOAD_CONST             120 (86)
           2589 LOAD_CONST              51 (32)
           2592 LOAD_CONST              22 (201)
           2595 LOAD_CONST              79 (151)
           2598 LOAD_CONST             203 (58)
           2601 LOAD_CONST              19 (7)
           2604 LOAD_CONST             201 (47)
           2607 LOAD_CONST             218 (192)
           2610 LOAD_CONST             187 (160)
           2613 LOAD_CONST             114 (27)
           2616 LOAD_CONST             102 (231)
           2619 LOAD_CONST              29 (140)
           2622 LOAD_CONST              90 (50)
           2625 LOAD_CONST              61 (157)
           2628 LOAD_CONST              93 (176)
           2631 LOAD_CONST              42 (144)
           2634 LOAD_CONST             162 (177)
           2637 LOAD_CONST             183 (181)
           2640 LOAD_CONST              94 (76)
           2643 LOAD_CONST              13 (96)
           2646 LOAD_CONST             171 (8)
           2649 LOAD_CONST              45 (23)
           2652 LOAD_CONST             178 (191)
           2655 LOAD_CONST             162 (177)
           2658 LOAD_CONST             104 (149)
           2661 LOAD_CONST              18 (227)
           2664 LOAD_CONST             192 (156)
           2667 LOAD_CONST             199 (136)
           2670 LOAD_CONST              97 (222)
           2673 LOAD_CONST               8 (57)
           2676 LOAD_CONST             228 (233)
           2679 LOAD_CONST             103 (196)
           2682 LOAD_CONST             193 (148)
           2685 LOAD_CONST              59 (21)
           2688 LOAD_CONST             233 (118)
           2691 LOAD_CONST             106 (85)
           2694 LOAD_CONST             109 (119)
           2697 LOAD_CONST             218 (192)
           2700 LOAD_CONST             104 (149)
           2703 LOAD_CONST              38 (171)
           2706 LOAD_CONST             232 (123)
           2709 LOAD_CONST              65 (4)
           2712 LOAD_CONST             171 (8)
           2715 LOAD_CONST              61 (157)
           2718 LOAD_CONST              82 (68)
           2721 LOAD_CONST             105 (113)
           2724 LOAD_CONST             182 (107)
           2727 LOAD_CONST             148 (28)
           2730 LOAD_CONST             111 (186)
           2733 LOAD_CONST             219 (193)
           2736 LOAD_CONST             189 (230)
           2739 LOAD_CONST             217 (26)
           2742 LOAD_CONST              13 (96)
           2745 LOAD_CONST             122 (132)
           2748 LOAD_CONST             158 (226)
           2751 LOAD_CONST             241 (244)
           2754 LOAD_CONST             139 (205)
           2757 LOAD_CONST             197 (63)
           2760 LOAD_CONST             194 (108)
           2763 LOAD_CONST               7 (10)
           2766 LOAD_CONST             171 (8)
           2769 LOAD_CONST              63 (17)
           2772 LOAD_CONST             188 (52)
           2775 LOAD_CONST             230 (249)
           2778 LOAD_CONST              88 (139)
           2781 LOAD_CONST             123 (56)
           2784 LOAD_CONST             117 (190)
           2787 LOAD_CONST              47 (102)
           2790 LOAD_CONST             209 (235)
           2793 LOAD_CONST             198 (92)
           2796 LOAD_CONST             178 (191)
           2799 LOAD_CONST              38 (171)
           2802 LOAD_CONST              20 (87)
           2805 LOAD_CONST             144 (122)
           2808 LOAD_CONST             238 (1)
           2811 LOAD_CONST             198 (92)
           2814 LOAD_CONST               2 (48)
           2817 LOAD_CONST              32 (209)
           2820 LOAD_CONST             133 (114)
           2823 LOAD_CONST             106 (85)
           2826 LOAD_CONST             227 (161)
           2829 LOAD_CONST             103 (196)
           2832 LOAD_CONST              92 (150)
           2835 LOAD_CONST             115 (215)
           2838 LOAD_CONST              98 (252)
           2841 LOAD_CONST              66 (14)
           2844 LOAD_CONST             111 (186)
           2847 LOAD_CONST              79 (151)
           2850 LOAD_CONST             247 (65)
           2853 LOAD_CONST              11 (73)
           2856 LOAD_CONST              27 (203)
           2859 LOAD_CONST              84 (111)
           2862 LOAD_CONST             208 (84)
           2865 LOAD_CONST              83 (59)
           2868 LOAD_CONST             177 (253)
           2871 LOAD_CONST              53 (228)
           2874 LOAD_CONST             185 (172)
           2877 LOAD_CONST              91 (199)
           2880 LOAD_CONST             210 (142)
           2883 LOAD_CONST             248 (80)
           2886 LOAD_CONST              91 (199)
           2889 LOAD_CONST             140 (49)
           2892 LOAD_CONST             222 (159)
           2895 LOAD_CONST             142 (116)
           2898 LOAD_CONST              55 (224)
           2901 LOAD_CONST              75 (115)
           2904 LOAD_CONST             107 (19)
           2907 LOAD_CONST             144 (122)
           2910 LOAD_CONST             168 (46)
           2913 LOAD_CONST              28 (5)
           2916 LOAD_CONST             183 (181)
           2919 LOAD_CONST             103 (196)
           2922 LOAD_CONST             140 (49)
           2925 LOAD_CONST              17 (210)
           2928 LOAD_CONST             147 (221)
           2931 LOAD_CONST              76 (25)
           2934 LOAD_CONST              54 (81)
           2937 LOAD_CONST             148 (28)
           2940 LOAD_CONST              78 (117)
           2943 LOAD_CONST              96 (127)
           2946 LOAD_CONST             150 (247)
           2949 LOAD_CONST               2 (48)
           2952 LOAD_CONST             182 (107)
           2955 LOAD_CONST             152 (106)
           2958 LOAD_CONST             127 (162)
           2961 LOAD_CONST              57 (129)
           2964 LOAD_CONST             234 (137)
           2967 LOAD_CONST             203 (58)
           2970 LOAD_CONST             187 (160)
           2973 LOAD_CONST              72 (194)
           2976 LOAD_CONST             203 (58)
           2979 LOAD_CONST             230 (249)
           2982 LOAD_CONST             200 (93)
           2985 LOAD_CONST              42 (144)
           2988 LOAD_CONST             162 (177)
           2991 LOAD_CONST             122 (132)
           2994 LOAD_CONST             193 (148)
           2997 LOAD_CONST             241 (244)
           3000 LOAD_CONST              48 (34)
           3003 LOAD_CONST             249 (179)
           3006 LOAD_CONST             100 (240)
           3009 LOAD_CONST             185 (172)
           3012 LOAD_CONST             244 (212)
           3015 LOAD_CONST              47 (102)
           3018 LOAD_CONST             207 (2)
           3021 LOAD_CONST             214 (206)
           3024 LOAD_CONST             200 (93)
           3027 LOAD_CONST             194 (108)
           3030 LOAD_CONST              87 (51)
           3033 LOAD_CONST             179 (109)
           3036 LOAD_CONST             166 (243)
           3039 LOAD_CONST             199 (136)
           3042 LOAD_CONST             173 (131)
           3045 LOAD_CONST             241 (244)
           3048 LOAD_CONST             111 (186)
           3051 LOAD_CONST              68 (0)
           3054 LOAD_CONST              89 (134)
           3057 LOAD_CONST             105 (113)
           3060 LOAD_CONST             177 (253)
           3063 LOAD_CONST             115 (215)
           3066 LOAD_CONST             148 (28)
           3069 LOAD_CONST              82 (68)
           3072 LOAD_CONST             134 (35)
           3075 LOAD_CONST              10 (72)
           3078 LOAD_CONST              61 (157)
           3081 LOAD_CONST              40 (208)
           3084 LOAD_CONST               6 (216)
           3087 LOAD_CONST               7 (10)
           3090 LOAD_CONST               8 (57)
           3093 LOAD_CONST             219 (193)
           3096 LOAD_CONST             179 (109)
           3099 LOAD_CONST             197 (63)
           3102 LOAD_CONST               8 (57)
           3105 LOAD_CONST             226 (103)
           3108 LOAD_CONST              14 (182)
           3111 LOAD_CONST              95 (18)
           3114 LOAD_CONST              16 (110)
           3117 LOAD_CONST              22 (201)
           3120 LOAD_CONST             132 (184)
           3123 LOAD_CONST             122 (132)
           3126 LOAD_CONST              79 (151)
           3129 LOAD_CONST              16 (110)
           3132 LOAD_CONST              45 (23)
           3135 LOAD_CONST             231 (164)
           3138 LOAD_CONST              72 (194)
           3141 LOAD_CONST              37 (225)
           3144 LOAD_CONST              25 (189)
           3147 LOAD_CONST              87 (51)
           3150 LOAD_CONST             235 (71)
           3153 LOAD_CONST             132 (184)
           3156 LOAD_CONST             179 (109)
           3159 LOAD_CONST              29 (140)
           3162 LOAD_CONST              30 (126)
           3165 LOAD_CONST              40 (208)
           3168 LOAD_CONST             156 (202)
           3171 LOAD_CONST              99 (128)
           3174 LOAD_CONST             223 (61)
           3177 LOAD_CONST             129 (100)
           3180 LOAD_CONST              87 (51)
           3183 LOAD_CONST             176 (135)
           3186 LOAD_CONST             156 (202)
           3189 LOAD_CONST              38 (171)
           3192 LOAD_CONST             173 (131)
           3195 LOAD_CONST               4 (238)
           3198 LOAD_CONST             138 (153)
           3201 LOAD_CONST             158 (226)
           3204 LOAD_CONST             108 (214)
           3207 LOAD_CONST              44 (155)
           3210 LOAD_CONST              75 (115)
           3213 LOAD_CONST              46 (255)
           3216 LOAD_CONST              95 (18)
           3219 LOAD_CONST             247 (65)
           3222 LOAD_CONST             245 (89)
           3225 LOAD_CONST              50 (141)
           3228 LOAD_CONST              94 (76)
           3231 LOAD_CONST              61 (157)
           3234 LOAD_CONST              57 (129)
           3237 LOAD_CONST              94 (76)
           3240 LOAD_CONST             242 (217)
           3243 LOAD_CONST              57 (129)
           3246 LOAD_CONST              67 (229)
           3249 LOAD_CONST              55 (224)
           3252 LOAD_CONST             194 (108)
           3255 LOAD_CONST              63 (17)
           3258 LOAD_CONST             238 (1)
           3261 LOAD_CONST              61 (157)
           3264 LOAD_CONST              30 (126)
           3267 LOAD_CONST             131 (198)
           3270 LOAD_CONST              12 (74)
           3273 LOAD_CONST              78 (117)
           3276 LOAD_CONST             182 (107)
           3279 LOAD_CONST             145 (121)
           3282 LOAD_CONST             125 (250)
           3285 LOAD_CONST              53 (228)
           3288 LOAD_CONST             171 (8)
           3291 LOAD_CONST              67 (229)
           3294 LOAD_CONST              77 (90)
           3297 LOAD_CONST              50 (141)
           3300 LOAD_CONST             113 (147)
           3303 LOAD_CONST             180 (200)
           3306 LOAD_CONST              37 (225)
           3309 LOAD_CONST              71 (120)
           3312 LOAD_CONST             111 (186)
           3315 LOAD_CONST             158 (226)
           3318 LOAD_CONST             238 (1)
           3321 LOAD_CONST              74 (178)
           3324 LOAD_CONST             184 (31)
           3327 LOAD_CONST             148 (28)
           3330 LOAD_CONST             135 (45)
           3333 LOAD_CONST             250 (78)
           3336 LOAD_CONST             213 (124)
           3339 LOAD_CONST              79 (151)
           3342 LOAD_CONST              27 (203)
           3345 LOAD_CONST             140 (49)
           3348 LOAD_CONST             152 (106)
           3351 LOAD_CONST              30 (126)
           3354 LOAD_CONST              51 (32)
           3357 LOAD_CONST              22 (201)
           3360 LOAD_CONST              67 (229)
           3363 LOAD_CONST             157 (95)
           3366 LOAD_CONST             251 (66)
           3369 LOAD_CONST              36 (64)
           3372 LOAD_CONST              14 (182)
           3375 LOAD_CONST             204 (197)
           3378 LOAD_CONST              87 (51)
           3381 LOAD_CONST             104 (149)
           3384 LOAD_CONST             122 (132)
           3387 LOAD_CONST              90 (50)
           3390 LOAD_CONST              61 (157)
           3393 LOAD_CONST             103 (196)
           3396 LOAD_CONST             211 (170)
           3399 LOAD_CONST              72 (194)
           3402 LOAD_CONST             108 (214)
           3405 LOAD_CONST             118 (62)
           3408 LOAD_CONST             232 (123)
           3411 LOAD_CONST             146 (29)
           3414 LOAD_CONST             163 (13)
           3417 LOAD_CONST              55 (224)
           3420 LOAD_CONST             174 (168)
           3423 LOAD_CONST             164 (246)
           3426 LOAD_CONST              99 (128)
           3429 LOAD_CONST              61 (157)
           3432 LOAD_CONST             199 (136)
           3435 LOAD_CONST             211 (170)
           3438 LOAD_CONST             252 (88)
           3441 LOAD_CONST             176 (135)
           3444 LOAD_CONST             191 (180)
           3447 LOAD_CONST             177 (253)
           3450 LOAD_CONST             145 (121)
           3453 LOAD_CONST             145 (121)
           3456 LOAD_CONST             106 (85)
           3459 LOAD_CONST             109 (119)
           3462 LOAD_CONST             218 (192)
           3465 LOAD_CONST             112 (165)
           3468 LOAD_CONST             253 (167)
           3471 LOAD_CONST             232 (123)
           3474 LOAD_CONST              65 (4)
           3477 LOAD_CONST             232 (123)
           3480 LOAD_CONST               9 (254)
           3483 LOAD_CONST             202 (69)
           3486 LOAD_CONST             109 (119)
           3489 LOAD_CONST             152 (106)
           3492 LOAD_CONST              78 (117)
           3495 LOAD_CONST             111 (186)
           3498 LOAD_CONST             186 (234)
           3501 LOAD_CONST             160 (154)
           3504 LOAD_CONST              63 (17)
           3507 LOAD_CONST             141 (97)
           3510 LOAD_CONST               4 (238)
           3513 LOAD_CONST             108 (214)
           3516 LOAD_CONST              99 (128)
           3519 LOAD_CONST              93 (176)
           3522 LOAD_CONST             118 (62)
           3525 LOAD_CONST             194 (108)
           3528 LOAD_CONST             250 (78)
           3531 LOAD_CONST             232 (123)
           3534 LOAD_CONST             106 (85)
           3537 LOAD_CONST             188 (52)
           3540 LOAD_CONST             122 (132)
           3543 LOAD_CONST             234 (137)
           3546 LOAD_CONST             123 (56)
           3549 LOAD_CONST              14 (182)
           3552 LOAD_CONST             226 (103)
           3555 LOAD_CONST             209 (235)
           3558 LOAD_CONST             126 (54)
           3561 LOAD_CONST             178 (191)
           3564 LOAD_CONST             138 (153)
           3567 LOAD_CONST              36 (64)
           3570 LOAD_CONST             203 (58)
           3573 LOAD_CONST             238 (1)
           3576 LOAD_CONST              51 (32)
           3579 LOAD_CONST              90 (50)
           3582 LOAD_CONST               4 (238)
           3585 LOAD_CONST              35 (9)
           3588 LOAD_CONST             152 (106)
           3591 LOAD_CONST             173 (131)
           3594 LOAD_CONST             138 (153)
           3597 LOAD_CONST              17 (210)
           3600 LOAD_CONST             132 (184)
           3603 LOAD_CONST              61 (157)
           3606 LOAD_CONST             184 (31)
           3609 LOAD_CONST             214 (206)
           3612 LOAD_CONST             161 (183)
           3615 LOAD_CONST              26 (70)
           3618 LOAD_CONST             135 (45)
           3621 LOAD_CONST             112 (165)
           3624 LOAD_CONST             142 (116)
           3627 LOAD_CONST             140 (49)
           3630 LOAD_CONST             250 (78)
           3633 LOAD_CONST             149 (16)
           3636 LOAD_CONST             122 (132)
           3639 LOAD_CONST              91 (199)
           3642 LOAD_CONST             162 (177)
           3645 LOAD_CONST             164 (246)
           3648 LOAD_CONST             166 (243)
           3651 LOAD_CONST             183 (181)
           3654 LOAD_CONST              10 (72)
           3657 LOAD_CONST              92 (150)
           3660 LOAD_CONST             148 (28)
           3663 LOAD_CONST             154 (143)
           3666 LOAD_CONST             194 (108)
           3669 LOAD_CONST             118 (62)
           3672 LOAD_CONST             124 (12)
           3675 LOAD_CONST             148 (28)
           3678 LOAD_CONST             169 (11)
           3681 LOAD_CONST             131 (198)
           3684 LOAD_CONST             137 (173)
           3687 LOAD_CONST              78 (117)
           3690 LOAD_CONST              53 (228)
           3693 LOAD_CONST             177 (253)
           3696 LOAD_CONST             200 (93)
           3699 LOAD_CONST             202 (69)
           3702 LOAD_CONST             143 (112)
           3705 LOAD_CONST             212 (20)
           3708 LOAD_CONST             182 (107)
           3711 LOAD_CONST             192 (156)
           3714 LOAD_CONST              54 (81)
           3717 LOAD_CONST              84 (111)
           3720 LOAD_CONST              12 (74)
           3723 LOAD_CONST              23 (207)
           3726 LOAD_CONST              99 (128)
           3729 LOAD_CONST              37 (225)
           3732 LOAD_CONST             200 (93)
           3735 LOAD_CONST             239 (163)
           3738 LOAD_CONST              74 (178)
           3741 LOAD_CONST             208 (84)
           3744 LOAD_CONST             114 (27)
           3747 LOAD_CONST             188 (52)
           3750 LOAD_CONST             159 (241)
           3753 LOAD_CONST             127 (162)
           3756 LOAD_CONST             231 (164)
           3759 LOAD_CONST             158 (226)
           3762 LOAD_CONST              52 (237)
           3765 LOAD_CONST             248 (80)
           3768 LOAD_CONST             218 (192)
           3771 LOAD_CONST              97 (222)
           3774 LOAD_CONST             103 (196)
           3777 LOAD_CONST             221 (130)
           3780 LOAD_CONST              28 (5)
           3783 LOAD_CONST             207 (2)
           3786 LOAD_CONST              61 (157)
           3789 LOAD_CONST              78 (117)
           3792 LOAD_CONST             182 (107)
           3795 LOAD_CONST              87 (51)
           3798 LOAD_CONST             179 (109)
           3801 LOAD_CONST             166 (243)
           3804 LOAD_CONST             131 (198)
           3807 LOAD_CONST             196 (245)
           3810 LOAD_CONST             166 (243)
           3813 LOAD_CONST             111 (186)
           3816 LOAD_CONST              68 (0)
           3819 LOAD_CONST             204 (197)
           3822 LOAD_CONST             149 (16)
           3825 LOAD_CONST              42 (144)
           3828 LOAD_CONST             178 (191)
           3831 LOAD_CONST              65 (4)
           3834 LOAD_CONST             130 (40)
           3837 LOAD_CONST             165 (83)
           3840 LOAD_CONST               3 (43)
           3843 LOAD_CONST               4 (238)
           3846 LOAD_CONST             253 (167)
           3849 LOAD_CONST               6 (216)
           3852 LOAD_CONST               7 (10)
           3855 LOAD_CONST             200 (93)
           3858 LOAD_CONST              46 (255)
           3861 LOAD_CONST              10 (72)
           3864 LOAD_CONST              23 (207)
           3867 LOAD_CONST             243 (75)
           3870 LOAD_CONST              13 (96)
           3873 LOAD_CONST             161 (183)
           3876 LOAD_CONST             233 (118)
           3879 LOAD_CONST              16 (110)
           3882 LOAD_CONST              17 (210)
           3885 LOAD_CONST              93 (176)
           3888 LOAD_CONST             234 (137)
           3891 LOAD_CONST             159 (241)
           3894 LOAD_CONST             106 (85)
           3897 LOAD_CONST              21 (38)
           3900 LOAD_CONST              22 (201)
           3903 LOAD_CONST              67 (229)
           3906 LOAD_CONST             180 (200)
           3909 LOAD_CONST             121 (36)
           3912 LOAD_CONST              87 (51)
           3915 LOAD_CONST             235 (71)
           3918 LOAD_CONST              27 (203)
           3921 LOAD_CONST             120 (86)
           3924 LOAD_CONST             102 (231)
           3927 LOAD_CONST             106 (85)
           3930 LOAD_CONST             177 (253)
           3933 LOAD_CONST              98 (252)
           3936 LOAD_CONST             164 (246)
           3939 LOAD_CONST              51 (32)
           3942 LOAD_CONST             121 (36)
           3945 LOAD_CONST             179 (109)
           3948 LOAD_CONST             174 (168)
           3951 LOAD_CONST             102 (231)
           3954 LOAD_CONST              89 (134)
           3957 LOAD_CONST             116 (174)
           3960 LOAD_CONST              98 (252)
           3963 LOAD_CONST             122 (132)
           3966 LOAD_CONST             102 (231)
           3969 LOAD_CONST             230 (249)
           3972 LOAD_CONST              14 (182)
           3975 LOAD_CONST             155 (94)
           3978 LOAD_CONST              17 (210)
           3981 LOAD_CONST             243 (75)
           3984 LOAD_CONST             182 (107)
           3987 LOAD_CONST             142 (116)
           3990 LOAD_CONST             187 (160)
           3993 LOAD_CONST             141 (97)
           3996 LOAD_CONST              72 (194)
           3999 LOAD_CONST              22 (201)
           4002 LOAD_CONST              63 (17)
           4005 LOAD_CONST             236 (152)
           4008 LOAD_CONST             139 (205)
           4011 LOAD_CONST              38 (171)
           4014 LOAD_CONST             174 (168)
           4017 LOAD_CONST             254 (53)
           4020 LOAD_CONST               8 (57)
           4023 LOAD_CONST             206 (44)
           4026 LOAD_CONST              14 (182)
           4029 LOAD_CONST             142 (116)
           4032 LOAD_CONST               5 (211)
           4035 LOAD_CONST              65 (4)
           4038 LOAD_CONST             140 (49)
           4041 LOAD_CONST             168 (46)
           4044 LOAD_CONST             153 (33)
           4047 LOAD_CONST              73 (242)
           4050 LOAD_CONST              91 (199)
           4053 LOAD_CONST             130 (40)
           4056 LOAD_CONST             204 (197)
           4059 LOAD_CONST             144 (122)
           4062 LOAD_CONST             242 (217)
           4065 LOAD_CONST              74 (178)
           4068 LOAD_CONST             150 (247)
           4071 LOAD_CONST              80 (145)
           4074 LOAD_CONST             106 (85)
           4077 LOAD_CONST             177 (253)
           4080 LOAD_CONST             128 (251)
           4083 LOAD_CONST             248 (80)
           4086 LOAD_CONST             128 (251)
           4089 LOAD_CONST             229 (77)
           4092 LOAD_CONST              54 (81)
           4095 LOAD_CONST             114 (27)
           4098 LOAD_CONST             142 (116)
           4101 LOAD_CONST             168 (46)
           4104 LOAD_CONST              23 (207)
           4107 LOAD_CONST             241 (244)
           4110 LOAD_CONST             247 (65)
           4113 LOAD_CONST             168 (46)
           4116 LOAD_CONST             233 (118)
           4119 LOAD_CONST              68 (0)
           4122 LOAD_CONST             228 (233)
           4125 LOAD_CONST             204 (197)
           4128 LOAD_CONST              96 (127)
           4131 LOAD_CONST              12 (74)
           4134 LOAD_CONST              13 (96)
           4137 LOAD_CONST              92 (150)
           4140 LOAD_CONST              67 (229)
           4143 LOAD_CONST             107 (19)
           4146 LOAD_CONST             131 (198)
           4149 LOAD_CONST             249 (179)
           4152 LOAD_CONST             245 (89)
           4155 LOAD_CONST              37 (225)
           4158 LOAD_CONST             214 (206)
           4161 LOAD_CONST             186 (234)
           4164 LOAD_CONST              80 (145)
           4167 LOAD_CONST             104 (149)
           4170 LOAD_CONST             194 (108)
           4173 LOAD_CONST             135 (45)
           4176 LOAD_CONST              28 (5)
           4179 LOAD_CONST              63 (17)
           4182 LOAD_CONST             211 (170)
           4185 LOAD_CONST             174 (168)
           4188 LOAD_CONST              99 (128)
           4191 LOAD_CONST             166 (243)
           4194 LOAD_CONST             253 (167)
           4197 LOAD_CONST             253 (167)
           4200 LOAD_CONST             159 (241)
           4203 LOAD_CONST             155 (94)
           4206 LOAD_CONST             173 (131)
           4209 LOAD_CONST              93 (176)
           4212 LOAD_CONST              98 (252)
           4215 LOAD_CONST              13 (96)
           4218 LOAD_CONST             107 (19)
           4221 LOAD_CONST             232 (123)
           4224 LOAD_CONST             212 (20)
           4227 LOAD_CONST             175 (175)
           4230 LOAD_CONST              24 (187)
           4233 LOAD_CONST             122 (132)
           4236 LOAD_CONST             169 (11)
           4239 LOAD_CONST             179 (109)
           4242 LOAD_CONST              35 (9)
           4245 LOAD_CONST             113 (147)
           4248 LOAD_CONST             172 (37)
           4251 LOAD_CONST             184 (31)
           4254 LOAD_CONST              58 (24)
           4257 LOAD_CONST              68 (0)
           4260 LOAD_CONST              44 (155)
           4263 LOAD_CONST              37 (225)
           4266 LOAD_CONST             231 (164)
           4269 LOAD_CONST             143 (112)
           4272 LOAD_CONST             148 (28)
           4275 LOAD_CONST             164 (246)
           4278 LOAD_CONST              98 (252)
           4281 LOAD_CONST             242 (217)
           4284 LOAD_CONST             192 (156)
           4287 LOAD_CONST             107 (19)
           4290 LOAD_CONST             247 (65)
           4293 LOAD_CONST             101 (99)
           4296 LOAD_CONST              71 (120)
           4299 LOAD_CONST              63 (17)
           4302 LOAD_CONST              76 (25)
           4305 LOAD_CONST              41 (169)
           4308 LOAD_CONST             231 (164)
           4311 LOAD_CONST              59 (21)
           4314 LOAD_CONST              39 (239)
           4317 LOAD_CONST             243 (75)
           4320 LOAD_CONST             131 (198)
           4323 LOAD_CONST             114 (27)
           4326 LOAD_CONST              69 (146)
           4329 LOAD_CONST              89 (134)
           4332 LOAD_CONST             167 (30)
           4335 LOAD_CONST             106 (85)
           4338 LOAD_CONST             206 (44)
           4341 LOAD_CONST             163 (13)
           4344 LOAD_CONST             184 (31)
           4347 LOAD_CONST              98 (252)
           4350 LOAD_CONST              11 (73)
           4353 LOAD_CONST             148 (28)
           4356 LOAD_CONST             154 (143)
           4359 LOAD_CONST             228 (233)
           4362 LOAD_CONST             216 (223)
           4365 LOAD_CONST               9 (254)
           4368 LOAD_CONST              32 (209)
           4371 LOAD_CONST             157 (95)
           4374 LOAD_CONST              92 (150)
           4377 LOAD_CONST             255 (188)
           4380 LOAD_CONST              81 (3)
           4383 LOAD_CONST              11 (73)
           4386 LOAD_CONST              27 (203)
           4389 LOAD_CONST             107 (19)
           4392 LOAD_CONST             120 (86)
           4395 LOAD_CONST              34 (105)
           4398 LOAD_CONST             133 (114)
           4401 LOAD_CONST              67 (229)
           4404 LOAD_CONST             185 (172)
           4407 LOAD_CONST              40 (208)
           4410 LOAD_CONST              93 (176)
           4413 LOAD_CONST               5 (211)
           4416 LOAD_CONST             204 (197)
           4419 LOAD_CONST             140 (49)
           4422 LOAD_CONST             158 (226)
           4425 LOAD_CONST             198 (92)
           4428 LOAD_CONST              55 (224)
           4431 LOAD_CONST             207 (2)
           4434 LOAD_CONST             167 (30)
           4437 LOAD_CONST             144 (122)
           4440 LOAD_CONST              54 (81)
           4443 LOAD_CONST             145 (121)
           4446 LOAD_CONST             183 (181)
           4449 LOAD_CONST             103 (196)
           4452 LOAD_CONST             106 (85)
           4455 LOAD_CONST             231 (164)
           4458 LOAD_CONST              43 (213)
           4461 LOAD_CONST             168 (46)
           4464 LOAD_CONST             206 (44)
           4467 LOAD_CONST             148 (28)
           4470 LOAD_CONST              11 (73)
           4473 LOAD_CONST             143 (112)
           4476 LOAD_CONST             193 (148)
           4479 LOAD_CONST             251 (66)
           4482 LOAD_CONST             195 (104)
           4485 LOAD_CONST             217 (26)
           4488 LOAD_CONST             108 (214)
           4491 LOAD_CONST              33 (219)
           4494 LOAD_CONST             128 (251)
           4497 LOAD_CONST             220 (60)
           4500 LOAD_CONST             103 (196)
           4503 LOAD_CONST              91 (199)
           4506 LOAD_CONST             203 (58)
           4509 LOAD_CONST              58 (24)
           4512 LOAD_CONST             118 (62)
           4515 LOAD_CONST              98 (252)
           4518 LOAD_CONST             112 (165)
           4521 LOAD_CONST             246 (236)
           4524 LOAD_CONST             128 (251)
           4527 LOAD_CONST             160 (154)
           4530 LOAD_CONST              48 (34)
           4533 LOAD_CONST             249 (179)
           4536 LOAD_CONST             161 (183)
           4539 LOAD_CONST              79 (151)
           4542 LOAD_CONST             191 (180)
           4545 LOAD_CONST              47 (102)
           4548 LOAD_CONST             207 (2)
           4551 LOAD_CONST              61 (157)
           4554 LOAD_CONST              78 (117)
           4557 LOAD_CONST             152 (106)
           4560 LOAD_CONST               2 (48)
           4563 LOAD_CONST              16 (110)
           4566 LOAD_CONST             160 (154)
           4569 LOAD_CONST             204 (197)
           4572 LOAD_CONST             150 (247)
           4575 LOAD_CONST             166 (243)
           4578 LOAD_CONST             111 (186)
           4581 LOAD_CONST              75 (115)
           4584 LOAD_CONST              62 (39)
           4587 LOAD_CONST             149 (16)
           4590 LOAD_CONST              42 (144)
           4593 LOAD_CONST             178 (191)
           4596 LOAD_CONST              10 (72)
           4599 LOAD_CONST             250 (78)
           4602 LOAD_CONST             149 (16)
           4605 LOAD_CONST              12 (74)
           4608 LOAD_CONST             192 (156)
           4611 LOAD_CONST              74 (178)
           4614 LOAD_CONST             181 (248)
           4617 LOAD_CONST             226 (103)
           4620 LOAD_CONST             198 (92)
           4623 LOAD_CONST              42 (144)
           4626 LOAD_CONST             201 (47)
           4629 LOAD_CONST               3 (43)
           4632 LOAD_CONST             197 (63)
           4635 LOAD_CONST              66 (14)
           4638 LOAD_CONST             115 (215)
           4641 LOAD_CONST             145 (121)
           4644 LOAD_CONST             224 (15)
           4647 LOAD_CONST             255 (188)
           4650 LOAD_CONST             242 (217)
           4653 LOAD_CONST              38 (171)
           4656 LOAD_CONST             125 (250)
           4659 LOAD_CONST             152 (106)
           4662 LOAD_CONST              82 (68)
           4665 LOAD_CONST             240 (185)
           4668 LOAD_CONST              17 (210)
           4671 LOAD_CONST              23 (207)
           4674 LOAD_CONST              43 (213)
           4677 LOAD_CONST             198 (92)
           4680 LOAD_CONST             237 (41)
           4683 LOAD_CONST             230 (249)
           4686 LOAD_CONST              11 (73)
           4689 LOAD_CONST             219 (193)
           4692 LOAD_CONST              83 (59)
           4695 LOAD_CONST               9 (254)
           4698 LOAD_CONST             227 (161)
           4701 LOAD_CONST             127 (162)
           4704 LOAD_CONST             135 (45)
           4707 LOAD_CONST              15 (82)
           4710 LOAD_CONST              21 (38)
           4713 LOAD_CONST             246 (236)
           4716 LOAD_CONST             256 (166)
           4719 LOAD_CONST             214 (206)
           4722 LOAD_CONST              97 (222)
           4725 LOAD_CONST             159 (241)
           4728 LOAD_CONST              73 (242)
           4731 LOAD_CONST             253 (167)
           4734 LOAD_CONST              24 (187)
           4737 LOAD_CONST              46 (255)
           4740 LOAD_CONST             110 (22)
           4743 LOAD_CONST             127 (162)
           4746 LOAD_CONST             194 (108)
           4749 LOAD_CONST             145 (121)
           4752 LOAD_CONST             188 (52)
           4755 LOAD_CONST             253 (167)
           4758 LOAD_CONST              75 (115)
           4761 LOAD_CONST              29 (140)
           4764 LOAD_CONST              41 (169)
           4767 LOAD_CONST             165 (83)
           4770 LOAD_CONST              32 (209)
           4773 LOAD_CONST              70 (133)
           4776 LOAD_CONST             255 (188)
           4779 LOAD_CONST             112 (165)
           4782 LOAD_CONST             123 (56)
           4785 LOAD_CONST               3 (43)
           4788 LOAD_CONST              34 (105)
           4791 LOAD_CONST             185 (172)
           4794 LOAD_CONST             155 (94)
           4797 LOAD_CONST              42 (144)
           4800 LOAD_CONST             235 (71)
           4803 LOAD_CONST             220 (60)
           4806 LOAD_CONST               2 (48)
           4809 LOAD_CONST             153 (33)
           4812 LOAD_CONST              52 (237)
           4815 LOAD_CONST             154 (143)
           4818 LOAD_CONST             243 (75)
           4821 LOAD_CONST              99 (128)
           4824 LOAD_CONST             205 (42)
           4827 LOAD_CONST             236 (152)
           4830 LOAD_CONST             189 (230)
           4833 LOAD_CONST              72 (194)
           4836 LOAD_CONST             190 (232)
           4839 LOAD_CONST             235 (71)
           4842 LOAD_CONST              41 (169)
           4845 LOAD_CONST             231 (164)
           4848 LOAD_CONST              51 (32)
           4851 LOAD_CONST              50 (141)
           4854 LOAD_CONST             213 (124)
           4857 LOAD_CONST             140 (49)
           4860 LOAD_CONST             129 (100)
           4863 LOAD_CONST             217 (26)
           4866 LOAD_CONST             251 (66)
           4869 LOAD_CONST              98 (252)
           4872 LOAD_CONST             236 (152)
           4875 LOAD_CONST             208 (84)
           4878 LOAD_CONST             226 (103)
           4881 LOAD_CONST             136 (55)
           4884 LOAD_CONST             250 (78)
           4887 LOAD_CONST             116 (174)
           4890 LOAD_CONST              39 (239)
           4893 LOAD_CONST             120 (86)
           4896 LOAD_CONST             106 (85)
           4899 LOAD_CONST             135 (45)
           4902 LOAD_CONST              70 (133)
           4905 LOAD_CONST              67 (229)
           4908 LOAD_CONST             124 (12)
           4911 LOAD_CONST              70 (133)
           4914 LOAD_CONST             227 (161)
           4917 LOAD_CONST             124 (12)
           4920 LOAD_CONST              25 (189)
           4923 LOAD_CONST             128 (251)
           4926 LOAD_CONST             128 (251)
           4929 LOAD_CONST             177 (253)
           4932 LOAD_CONST             244 (212)
           4935 LOAD_CONST             153 (33)
           4938 LOAD_CONST             143 (112)
           4941 LOAD_CONST             124 (12)
           4944 LOAD_CONST             163 (13)
           4947 LOAD_CONST             244 (212)
           4950 LOAD_CONST              18 (227)
           4953 LOAD_CONST             236 (152)
           4956 LOAD_CONST             170 (195)
           4959 LOAD_CONST              73 (242)
           4962 LOAD_CONST             189 (230)
           4965 LOAD_CONST             211 (170)
           4968 LOAD_CONST             120 (86)
           4971 LOAD_CONST             221 (130)
           4974 LOAD_CONST               9 (254)
           4977 LOAD_CONST             191 (180)
           4980 LOAD_CONST             205 (42)
           4983 LOAD_CONST             149 (16)
           4986 LOAD_CONST             172 (37)
           4989 LOAD_CONST              66 (14)
           4992 LOAD_CONST             191 (180)
           4995 LOAD_CONST             117 (190)
           4998 LOAD_CONST             103 (196)
           5001 LOAD_CONST              59 (21)
           5004 LOAD_CONST             126 (54)
           5007 LOAD_CONST              49 (91)
           5010 LOAD_CONST             249 (179)
           5013 LOAD_CONST             238 (1)
           5016 LOAD_CONST             157 (95)
           5019 LOAD_CONST             114 (27)
           5022 LOAD_CONST             238 (1)
           5025 LOAD_CONST              44 (155)
           5028 LOAD_CONST               4 (238)
           5031 LOAD_CONST             190 (232)
           5034 LOAD_CONST              96 (127)
           5037 LOAD_CONST              81 (3)
           5040 LOAD_CONST              61 (157)
           5043 LOAD_CONST             112 (165)
           5046 LOAD_CONST              42 (144)
           5049 LOAD_CONST             257 (158)
           5052 LOAD_CONST             252 (88)
           5055 LOAD_CONST              28 (5)
           5058 LOAD_CONST              48 (34)
           5061 LOAD_CONST               2 (48)
           5064 LOAD_CONST              95 (18)
           5067 LOAD_CONST              82 (68)
           5070 LOAD_CONST             177 (253)
           5073 LOAD_CONST              41 (169)
           5076 LOAD_CONST               7 (10)
           5079 LOAD_CONST              38 (171)
           5082 LOAD_CONST             226 (103)
           5085 LOAD_CONST             209 (235)
           5088 LOAD_CONST             126 (54)
           5091 LOAD_CONST             178 (191)
           5094 LOAD_CONST             216 (223)
           5097 LOAD_CONST              90 (50)
           5100 LOAD_CONST              71 (120)
           5103 LOAD_CONST             238 (1)
           5106 LOAD_CONST              51 (32)
           5109 LOAD_CONST              36 (64)
           5112 LOAD_CONST             127 (162)
           5115 LOAD_CONST             133 (114)
           5118 LOAD_CONST             140 (49)
           5121 LOAD_CONST             127 (162)
           5124 LOAD_CONST             103 (196)
           5127 LOAD_CONST             139 (205)
           5130 LOAD_CONST             117 (190)
           5133 LOAD_CONST             253 (167)
           5136 LOAD_CONST             165 (83)
           5139 LOAD_CONST             189 (230)
           5142 LOAD_CONST             161 (183)
           5145 LOAD_CONST             194 (108)
           5148 LOAD_CONST             237 (41)
           5151 LOAD_CONST             185 (172)
           5154 LOAD_CONST             133 (114)
           5157 LOAD_CONST             203 (58)
           5160 LOAD_CONST             114 (27)
           5163 LOAD_CONST             107 (19)
           5166 LOAD_CONST              99 (128)
           5169 LOAD_CONST             219 (193)
           5172 LOAD_CONST              74 (178)
           5175 LOAD_CONST              52 (237)
           5178 LOAD_CONST             132 (184)
           5181 LOAD_CONST             231 (164)
           5184 LOAD_CONST              63 (17)
           5187 LOAD_CONST             147 (221)
           5190 LOAD_CONST              45 (23)
           5193 LOAD_CONST             234 (137)
           5196 LOAD_CONST              68 (0)
           5199 LOAD_CONST             167 (30)
           5202 LOAD_CONST             144 (122)
           5205 LOAD_CONST             145 (121)
           5208 LOAD_CONST             163 (13)
           5211 LOAD_CONST             191 (180)
           5214 LOAD_CONST             103 (196)
           5217 LOAD_CONST             106 (85)
           5220 LOAD_CONST             115 (215)
           5223 LOAD_CONST             246 (236)
           5226 LOAD_CONST              77 (90)
           5229 LOAD_CONST             135 (45)
           5232 LOAD_CONST             148 (28)
           5235 LOAD_CONST              78 (117)
           5238 LOAD_CONST              81 (3)
           5241 LOAD_CONST             103 (196)
           5244 LOAD_CONST             215 (67)
           5247 LOAD_CONST             217 (26)
           5250 LOAD_CONST             152 (106)
           5253 LOAD_CONST             127 (162)
           5256 LOAD_CONST              67 (229)
           5259 LOAD_CONST              93 (176)
           5262 LOAD_CONST              20 (87)
           5265 LOAD_CONST             222 (159)
           5268 LOAD_CONST             189 (230)
           5271 LOAD_CONST             226 (103)
           5274 LOAD_CONST              77 (90)
           5277 LOAD_CONST              95 (18)
           5280 LOAD_CONST              46 (255)
           5283 LOAD_CONST             174 (168)
           5286 LOAD_CONST              37 (225)
           5289 LOAD_CONST             191 (180)
           5292 LOAD_CONST             161 (183)
           5295 LOAD_CONST             247 (65)
           5298 LOAD_CONST              92 (150)
           5301 LOAD_CONST             103 (196)
           5304 LOAD_CONST              33 (219)
           5307 LOAD_CONST             147 (221)
           5310 LOAD_CONST              26 (70)
           5313 LOAD_CONST             233 (118)
           5316 LOAD_CONST             241 (244)
           5319 LOAD_CONST              63 (17)
           5322 LOAD_CONST               7 (10)
           5325 LOAD_CONST             252 (88)
           5328 LOAD_CONST             229 (77)
           5331 LOAD_CONST              69 (146)
           5334 LOAD_CONST             127 (162)
           5337 LOAD_CONST              92 (150)
           5340 LOAD_CONST              99 (128)
           5343 LOAD_CONST              74 (178)
           5346 LOAD_CONST              68 (0)
           5349 LOAD_CONST              89 (134)
           5352 LOAD_CONST             149 (16)
           5355 LOAD_CONST             185 (172)
           5358 LOAD_CONST              86 (204)
           5361 LOAD_CONST             212 (20)
           5364 LOAD_CONST             208 (84)
           5367 LOAD_CONST             203 (58)
           5370 LOAD_CONST              49 (91)
           5373 LOAD_CONST             160 (154)
           5376 LOAD_CONST              52 (237)
           5379 LOAD_CONST             185 (172)
           5382 LOAD_CONST              66 (14)
           5385 LOAD_CONST               8 (57)
           5388 LOAD_CONST               9 (254)
           5391 LOAD_CONST              10 (72)
           5394 LOAD_CONST             237 (41)
           5397 LOAD_CONST              90 (50)
           5400 LOAD_CONST              28 (5)
           5403 LOAD_CONST              43 (213)
           5406 LOAD_CONST             141 (97)
           5409 LOAD_CONST             144 (122)
           5412 LOAD_CONST              17 (210)
           5415 LOAD_CONST              18 (227)
           5418 LOAD_CONST             227 (161)
           5421 LOAD_CONST              86 (204)
           5424 LOAD_CONST             123 (56)
           5427 LOAD_CONST              13 (96)
           5430 LOAD_CONST             187 (160)
           5433 LOAD_CONST              91 (199)
           5436 LOAD_CONST              97 (222)
           5439 LOAD_CONST              61 (157)
           5442 LOAD_CONST             235 (71)
           5445 LOAD_CONST             168 (46)
           5448 LOAD_CONST             175 (175)
           5451 LOAD_CONST             171 (8)
           5454 LOAD_CONST             102 (231)
           5457 LOAD_CONST             155 (94)
           5460 LOAD_CONST             239 (163)
           5463 LOAD_CONST             231 (164)
           5466 LOAD_CONST              38 (171)
           5469 LOAD_CONST             225 (125)
           5472 LOAD_CONST              47 (102)
           5475 LOAD_CONST              90 (50)
           5478 LOAD_CONST             159 (241)
           5481 LOAD_CONST              41 (169)
           5484 LOAD_CONST              38 (171)
           5487 LOAD_CONST             173 (131)
           5490 LOAD_CONST              32 (209)
           5493 LOAD_CONST              41 (169)
           5496 LOAD_CONST             156 (202)
           5499 LOAD_CONST             244 (212)
           5502 LOAD_CONST              44 (155)
           5505 LOAD_CONST              75 (115)
           5508 LOAD_CONST              98 (252)
           5511 LOAD_CONST              47 (102)
           5514 LOAD_CONST              26 (70)
           5517 LOAD_CONST             245 (89)
           5520 LOAD_CONST             214 (206)
           5523 LOAD_CONST              94 (76)
           5526 LOAD_CONST              39 (239)
           5529 LOAD_CONST              53 (228)
           5532 LOAD_CONST             119 (79)
           5535 LOAD_CONST             132 (184)
           5538 LOAD_CONST              55 (224)
           5541 LOAD_CONST              89 (134)
           5544 LOAD_CONST              70 (133)
           5547 LOAD_CONST             194 (108)
           5550 LOAD_CONST             212 (20)
           5553 LOAD_CONST             238 (1)
           5556 LOAD_CONST             230 (249)
           5559 LOAD_CONST              96 (127)
           5562 LOAD_CONST             175 (175)
           5565 LOAD_CONST              36 (64)
           5568 LOAD_CONST             107 (19)
           5571 LOAD_CONST              66 (14)
           5574 LOAD_CONST             221 (130)
           5577 LOAD_CONST              40 (208)
           5580 LOAD_CONST             102 (231)
           5583 LOAD_CONST              49 (91)
           5586 LOAD_CONST             139 (205)
           5589 LOAD_CONST             245 (89)
           5592 LOAD_CONST             230 (249)
           5595 LOAD_CONST              69 (146)
           5598 LOAD_CONST             180 (200)
           5601 LOAD_CONST             175 (175)
           5604 LOAD_CONST              63 (17)
           5607 LOAD_CONST              72 (194)
           5610 LOAD_CONST              92 (150)
           5613 LOAD_CONST              68 (0)
           5616 LOAD_CONST              74 (178)
           5619 LOAD_CONST             233 (118)
           5622 LOAD_CONST              18 (227)
           5625 LOAD_CONST              77 (90)
           5628 LOAD_CONST             203 (58)
           5631 LOAD_CONST             225 (125)
           5634 LOAD_CONST             178 (191)
           5637 LOAD_CONST             156 (202)
           5640 LOAD_CONST             140 (49)
           5643 LOAD_CONST              81 (3)
           5646 LOAD_CONST             120 (86)
           5649 LOAD_CONST             208 (84)
           5652 LOAD_CONST             180 (200)
           5655 LOAD_CONST              67 (229)
           5658 LOAD_CONST             157 (95)
           5661 LOAD_CONST             152 (106)
           5664 LOAD_CONST              95 (18)
           5667 LOAD_CONST             257 (158)
           5670 LOAD_CONST             204 (197)
           5673 LOAD_CONST              87 (51)
           5676 LOAD_CONST             189 (230)
           5679 LOAD_CONST              29 (140)
           5682 LOAD_CONST             217 (26)
           5685 LOAD_CONST              61 (157)
           5688 LOAD_CONST             103 (196)
           5691 LOAD_CONST              92 (150)
           5694 LOAD_CONST             162 (177)
           5697 LOAD_CONST              61 (157)
           5700 LOAD_CONST              94 (76)
           5703 LOAD_CONST              95 (18)
           5706 LOAD_CONST             179 (109)
           5709 LOAD_CONST             145 (121)
           5712 LOAD_CONST             137 (173)
           5715 LOAD_CONST             244 (212)
           5718 LOAD_CONST             100 (240)
           5721 LOAD_CONST              99 (128)
           5724 LOAD_CONST              61 (157)
           5727 LOAD_CONST             191 (180)
           5730 LOAD_CONST             137 (173)
           5733 LOAD_CONST              77 (90)
           5736 LOAD_CONST             236 (152)
           5739 LOAD_CONST             137 (173)
           5742 LOAD_CONST              53 (228)
           5745 LOAD_CONST             141 (97)
           5748 LOAD_CONST             119 (79)
           5751 LOAD_CONST             153 (33)
           5754 LOAD_CONST              96 (127)
           5757 LOAD_CONST             218 (192)
           5760 LOAD_CONST             108 (214)
           5763 LOAD_CONST              38 (171)
           5766 LOAD_CONST             235 (71)
           5769 LOAD_CONST             195 (104)
           5772 LOAD_CONST             217 (26)
           5775 LOAD_CONST             113 (147)
           5778 LOAD_CONST              21 (38)
           5781 LOAD_CONST              59 (21)
           5784 LOAD_CONST               7 (10)
           5787 LOAD_CONST              26 (70)
           5790 LOAD_CONST              31 (138)
           5793 LOAD_CONST             219 (193)
           5796 LOAD_CONST              44 (155)
           5799 LOAD_CONST             114 (27)
           5802 LOAD_CONST             107 (19)
           5805 LOAD_CONST              98 (252)
           5808 LOAD_CONST             115 (215)
           5811 LOAD_CONST             241 (244)
           5814 LOAD_CONST             162 (177)
           5817 LOAD_CONST              20 (87)
           5820 LOAD_CONST             113 (147)
           5823 LOAD_CONST             250 (78)
           5826 LOAD_CONST             106 (85)
           5829 LOAD_CONST             220 (60)
           5832 LOAD_CONST              20 (87)
           5835 LOAD_CONST              89 (134)
           5838 LOAD_CONST             234 (137)
           5841 LOAD_CONST             123 (56)
           5844 LOAD_CONST              72 (194)
           5847 LOAD_CONST             101 (99)
           5850 LOAD_CONST             209 (235)
           5853 LOAD_CONST             126 (54)
           5856 LOAD_CONST             178 (191)
           5859 LOAD_CONST             116 (174)
           5862 LOAD_CONST              87 (51)
           5865 LOAD_CONST              71 (120)
           5868 LOAD_CONST             238 (1)
           5871 LOAD_CONST             101 (99)
           5874 LOAD_CONST              90 (50)
           5877 LOAD_CONST              32 (209)
           5880 LOAD_CONST             129 (100)
           5883 LOAD_CONST             251 (66)
           5886 LOAD_CONST              21 (38)
           5889 LOAD_CONST             103 (196)
           5892 LOAD_CONST              73 (242)
           5895 LOAD_CONST               5 (211)
           5898 LOAD_CONST             236 (152)
           5901 LOAD_CONST              75 (115)
           5904 LOAD_CONST              24 (187)
           5907 LOAD_CONST             186 (234)
           5910 LOAD_CONST             237 (41)
           5913 LOAD_CONST              10 (72)
           5916 LOAD_CONST             175 (175)
           5919 LOAD_CONST              45 (23)
           5922 LOAD_CONST             120 (86)
           5925 LOAD_CONST             226 (103)
           5928 LOAD_CONST             213 (124)
           5931 LOAD_CONST              67 (229)
           5934 LOAD_CONST              32 (209)
           5937 LOAD_CONST               5 (211)
           5940 LOAD_CONST             236 (152)
           5943 LOAD_CONST             116 (174)
           5946 LOAD_CONST             219 (193)
           5949 LOAD_CONST             140 (49)
           5952 LOAD_CONST             160 (154)
           5955 LOAD_CONST             184 (31)
           5958 LOAD_CONST              55 (224)
           5961 LOAD_CONST              30 (126)
           5964 LOAD_CONST             146 (29)
           5967 LOAD_CONST             144 (122)
           5970 LOAD_CONST             163 (13)
           5973 LOAD_CONST             145 (121)
           5976 LOAD_CONST             183 (181)
           5979 LOAD_CONST             132 (184)
           5982 LOAD_CONST             106 (85)
           5985 LOAD_CONST             115 (215)
           5988 LOAD_CONST             155 (94)
           5991 LOAD_CONST             201 (47)
           5994 LOAD_CONST             206 (44)
           5997 LOAD_CONST             109 (119)
           6000 LOAD_CONST             143 (112)
           6003 LOAD_CONST              81 (3)
           6006 LOAD_CONST              70 (133)
           6009 LOAD_CONST             114 (27)
           6012 LOAD_CONST             238 (1)
           6015 LOAD_CONST             203 (58)
           6018 LOAD_CONST              86 (204)
           6021 LOAD_CONST              67 (229)
           6024 LOAD_CONST             154 (143)
           6027 LOAD_CONST              26 (70)
           6030 LOAD_CONST             218 (192)
           6033 LOAD_CONST              91 (199)
           6036 LOAD_CONST             250 (78)
           6039 LOAD_CONST             144 (122)
           6042 LOAD_CONST             157 (95)
           6045 LOAD_CONST             246 (236)
           6048 LOAD_CONST             139 (205)
           6051 LOAD_CONST             122 (132)
           6054 LOAD_CONST              45 (23)
           6057 LOAD_CONST             234 (137)
           6060 LOAD_CONST              48 (34)
           6063 LOAD_CONST               6 (216)
           6066 LOAD_CONST              74 (178)
           6069 LOAD_CONST              53 (228)
           6072 LOAD_CONST              72 (194)
           6075 LOAD_CONST              51 (32)
           6078 LOAD_CONST             207 (2)
           6081 LOAD_CONST             230 (249)
           6084 LOAD_CONST             109 (119)
           6087 LOAD_CONST             182 (107)
           6090 LOAD_CONST             250 (78)
           6093 LOAD_CONST              34 (105)
           6096 LOAD_CONST             166 (243)
           6099 LOAD_CONST             174 (168)
           6102 LOAD_CONST             150 (247)
           6105 LOAD_CONST             166 (243)
           6108 LOAD_CONST             131 (198)
           6111 LOAD_CONST             207 (2)
           6114 LOAD_CONST              89 (134)
           6117 LOAD_CONST             129 (100)
           6120 LOAD_CONST              80 (145)
           6123 LOAD_CONST             178 (191)
           6126 LOAD_CONST              81 (3)
           6129 LOAD_CONST             121 (36)
           6132 LOAD_CONST             165 (83)
           6135 LOAD_CONST              20 (87)
           6138 LOAD_CONST               4 (238)
           6141 LOAD_CONST               5 (211)
           6144 LOAD_CONST             231 (164)
           6147 LOAD_CONST              35 (9)
           6150 LOAD_CONST               8 (57)
           6153 LOAD_CONST             102 (231)
           6156 LOAD_CONST              27 (203)
           6159 LOAD_CONST             229 (77)
           6162 LOAD_CONST              12 (74)
           6165 LOAD_CONST             148 (28)
           6168 LOAD_CONST             161 (183)
           6171 LOAD_CONST              95 (18)
           6174 LOAD_CONST              95 (18)
           6177 LOAD_CONST             108 (214)
           6180 LOAD_CONST              18 (227)
           6183 LOAD_CONST             132 (184)
           6186 LOAD_CONST              74 (178)
           6189 LOAD_CONST             108 (214)
           6192 LOAD_CONST              62 (39)
           6195 LOAD_CONST              22 (201)
           6198 LOAD_CONST             192 (156)
           6201 LOAD_CONST             131 (198)
           6204 LOAD_CONST             178 (191)
           6207 LOAD_CONST              87 (51)
           6210 LOAD_CONST              83 (59)
           6213 LOAD_CONST             180 (200)
           6216 LOAD_CONST              34 (105)
           6219 LOAD_CONST             190 (232)
           6222 LOAD_CONST             225 (125)
           6225 LOAD_CONST              40 (208)
           6228 LOAD_CONST             189 (230)
           6231 LOAD_CONST             256 (166)
           6234 LOAD_CONST              66 (14)
           6237 LOAD_CONST              35 (9)
           6240 LOAD_CONST             220 (60)
           6243 LOAD_CONST              57 (129)
           6246 LOAD_CONST             156 (202)
           6249 LOAD_CONST              23 (207)
           6252 LOAD_CONST              99 (128)
           6255 LOAD_CONST              32 (209)
           6258 LOAD_CONST             257 (158)
           6261 LOAD_CONST             161 (183)
           6264 LOAD_CONST              40 (208)
           6267 LOAD_CONST              44 (155)
           6270 LOAD_CONST             207 (2)
           6273 LOAD_CONST             186 (234)
           6276 LOAD_CONST              47 (102)
           6279 LOAD_CONST              63 (17)
           6282 LOAD_CONST             172 (37)
           6285 LOAD_CONST             154 (143)
           6288 LOAD_CONST              94 (76)
           6291 LOAD_CONST             255 (188)
           6294 LOAD_CONST              86 (204)
           6297 LOAD_CONST               8 (57)
           6300 LOAD_CONST             183 (181)
           6303 LOAD_CONST              55 (224)
           6306 LOAD_CONST              89 (134)
           6309 LOAD_CONST              27 (203)
           6312 LOAD_CONST             194 (108)
           6315 LOAD_CONST             212 (20)
           6318 LOAD_CONST             238 (1)
           6321 LOAD_CONST              61 (157)
           6324 LOAD_CONST              30 (126)
           6327 LOAD_CONST             131 (198)
           6330 LOAD_CONST             121 (36)
           6333 LOAD_CONST              63 (17)
           6336 LOAD_CONST              66 (14)
           6339 LOAD_CONST             238 (1)
           6342 LOAD_CONST              24 (187)
           6345 LOAD_CONST             189 (230)
           6348 LOAD_CONST             171 (8)
           6351 LOAD_CONST              67 (229)
           6354 LOAD_CONST              77 (90)
           6357 LOAD_CONST              32 (209)
           6360 LOAD_CONST              42 (144)
           6363 LOAD_CONST             180 (200)
           6366 LOAD_CONST              37 (225)
           6369 LOAD_CONST              71 (120)
           6372 LOAD_CONST              38 (171)
           6375 LOAD_CONST              92 (150)
           6378 LOAD_CONST              68 (0)
           6381 LOAD_CONST              74 (178)
           6384 LOAD_CONST             184 (31)
           6387 LOAD_CONST              78 (117)
           6390 LOAD_CONST              77 (90)
           6393 LOAD_CONST             203 (58)
           6396 LOAD_CONST             225 (125)
           6399 LOAD_CONST              79 (151)
           6402 LOAD_CONST              18 (227)
           6405 LOAD_CONST              90 (50)
           6408 LOAD_CONST              81 (3)
           6411 LOAD_CONST             120 (86)
           6414 LOAD_CONST              51 (32)
           6417 LOAD_CONST              25 (189)
           6420 LOAD_CONST             189 (230)
           6423 LOAD_CONST             157 (95)
           6426 LOAD_CONST             152 (106)
           6429 LOAD_CONST              36 (64)
           6432 LOAD_CONST              85 (218)
           6435 LOAD_CONST             187 (160)
           6438 LOAD_CONST             200 (93)
           6441 LOAD_CONST              69 (146)
           6444 LOAD_CONST             154 (143)
           6447 LOAD_CONST              90 (50)
           6450 LOAD_CONST              61 (157)
           6453 LOAD_CONST             103 (196)
           6456 LOAD_CONST             196 (245)
           6459 LOAD_CONST             242 (217)
           6462 LOAD_CONST              91 (199)
           6465 LOAD_CONST             123 (56)
           6468 LOAD_CONST              63 (17)
           6471 LOAD_CONST             179 (109)
           6474 LOAD_CONST             145 (121)
           6477 LOAD_CONST              97 (222)
           6480 LOAD_CONST             249 (179)
           6483 LOAD_CONST             221 (130)
           6486 LOAD_CONST              53 (228)
           6489 LOAD_CONST             183 (181)
           6492 LOAD_CONST              50 (141)
           6495 LOAD_CONST              97 (222)
           6498 LOAD_CONST               8 (57)
           6501 LOAD_CONST             186 (234)
           6504 LOAD_CONST              93 (176)
           6507 LOAD_CONST             104 (149)
           6510 LOAD_CONST              59 (21)
           6513 LOAD_CONST             105 (113)
           6516 LOAD_CONST             106 (85)
           6519 LOAD_CONST             107 (19)
           6522 LOAD_CONST             191 (180)
           6525 LOAD_CONST             115 (215)
           6528 LOAD_CONST              38 (171)
           6531 LOAD_CONST             232 (123)
           6534 LOAD_CONST              65 (4)
           6537 LOAD_CONST             149 (16)
           6540 LOAD_CONST              31 (138)
           6543 LOAD_CONST             202 (69)
           6546 LOAD_CONST             105 (113)
           6549 LOAD_CONST             182 (107)
           6552 LOAD_CONST              71 (120)
           6555 LOAD_CONST              97 (222)
           6558 LOAD_CONST             113 (147)
           6561 LOAD_CONST              42 (144)
           6564 LOAD_CONST             114 (27)
           6567 LOAD_CONST              13 (96)
           6570 LOAD_CONST              98 (252)
           6573 LOAD_CONST             239 (163)
           6576 LOAD_CONST             196 (245)
           6579 LOAD_CONST             162 (177)
           6582 LOAD_CONST             118 (62)
           6585 LOAD_CONST             194 (108)
           6588 LOAD_CONST             121 (36)
           6591 LOAD_CONST             225 (125)
           6594 LOAD_CONST             220 (60)
           6597 LOAD_CONST             188 (52)
           6600 LOAD_CONST             122 (132)
           6603 LOAD_CONST             234 (137)
           6606 LOAD_CONST             149 (16)
           6609 LOAD_CONST              72 (194)
           6612 LOAD_CONST              47 (102)
           6615 LOAD_CONST             209 (235)
           6618 LOAD_CONST             126 (54)
           6621 LOAD_CONST              86 (204)
           6624 LOAD_CONST             239 (163)
           6627 LOAD_CONST              87 (51)
           6630 LOAD_CONST              71 (120)
           6633 LOAD_CONST             238 (1)
           6636 LOAD_CONST             148 (28)
           6639 LOAD_CONST             247 (65)
           6642 LOAD_CONST              74 (178)
           6645 LOAD_CONST             110 (22)
           6648 LOAD_CONST             252 (88)
           6651 LOAD_CONST              17 (210)
           6654 LOAD_CONST              93 (176)
           6657 LOAD_CONST              86 (204)
           6660 LOAD_CONST             253 (167)
           6663 LOAD_CONST              46 (255)
           6666 LOAD_CONST             133 (114)
           6669 LOAD_CONST              24 (187)
           6672 LOAD_CONST              79 (151)
           6675 LOAD_CONST             250 (78)
           6678 LOAD_CONST              21 (38)
           6681 LOAD_CONST             174 (168)
           6684 LOAD_CONST              62 (39)
           6687 LOAD_CONST             120 (86)
           6690 LOAD_CONST              83 (59)
           6693 LOAD_CONST              30 (126)
           6696 LOAD_CONST              92 (150)
           6699 LOAD_CONST             111 (186)
           6702 LOAD_CONST              40 (208)
           6705 LOAD_CONST             236 (152)
           6708 LOAD_CONST               5 (211)
           6711 LOAD_CONST             204 (197)
           6714 LOAD_CONST               2 (48)
           6717 LOAD_CONST              53 (228)
           6720 LOAD_CONST              78 (117)
           6723 LOAD_CONST             246 (236)
           6726 LOAD_CONST              81 (3)
           6729 LOAD_CONST             146 (29)
           6732 LOAD_CONST             232 (123)
           6735 LOAD_CONST             182 (107)
           6738 LOAD_CONST             145 (121)
           6741 LOAD_CONST             162 (177)
           6744 LOAD_CONST             204 (197)
           6747 LOAD_CONST             235 (71)
           6750 LOAD_CONST             115 (215)
           6753 LOAD_CONST             244 (212)
           6756 LOAD_CONST             201 (47)
           6759 LOAD_CONST              66 (14)
           6762 LOAD_CONST             146 (29)
           6765 LOAD_CONST              96 (127)
           6768 LOAD_CONST             207 (2)
           6771 LOAD_CONST             230 (249)
           6774 LOAD_CONST             140 (49)
           6777 LOAD_CONST              64 (98)
           6780 LOAD_CONST             195 (104)
           6783 LOAD_CONST             127 (162)
           6786 LOAD_CONST              67 (229)
           6789 LOAD_CONST             154 (143)
           6792 LOAD_CONST             223 (61)
           6795 LOAD_CONST             103 (196)
           6798 LOAD_CONST              91 (199)
           6801 LOAD_CONST             203 (58)
           6804 LOAD_CONST              96 (127)
           6807 LOAD_CONST             157 (95)
           6810 LOAD_CONST              42 (144)
           6813 LOAD_CONST              86 (204)
           6816 LOAD_CONST              91 (199)
           6819 LOAD_CONST             193 (148)
           6822 LOAD_CONST             199 (136)
           6825 LOAD_CONST              48 (34)
           6828 LOAD_CONST             218 (192)
           6831 LOAD_CONST             207 (2)
           6834 LOAD_CONST              53 (228)
           6837 LOAD_CONST              93 (176)
           6840 LOAD_CONST              47 (102)
           6843 LOAD_CONST              60 (101)
           6846 LOAD_CONST              61 (157)
           6849 LOAD_CONST              78 (117)
           6852 LOAD_CONST             110 (22)
           6855 LOAD_CONST             140 (49)
           6858 LOAD_CONST             179 (109)
           6861 LOAD_CONST             193 (148)
           6864 LOAD_CONST             131 (198)
           6867 LOAD_CONST             150 (247)
           6870 LOAD_CONST             210 (142)
           6873 LOAD_CONST             240 (185)
           6876 LOAD_CONST              68 (0)
           6879 LOAD_CONST               9 (254)
           6882 LOAD_CONST             136 (55)
           6885 LOAD_CONST              42 (144)
           6888 LOAD_CONST             170 (195)
           6891 LOAD_CONST             109 (119)
           6894 LOAD_CONST              21 (38)
           6897 LOAD_CONST              45 (23)
           6900 LOAD_CONST             233 (118)
           6903 LOAD_CONST             159 (241)
           6906 LOAD_CONST               5 (211)
           6909 LOAD_CONST             112 (165)
           6912 LOAD_CONST              66 (14)
           6915 LOAD_CONST               8 (57)
           6918 LOAD_CONST             221 (130)
           6921 LOAD_CONST              12 (74)
           6924 LOAD_CONST              94 (76)
           6927 LOAD_CONST              51 (32)
           6930 LOAD_CONST              13 (96)
           6933 LOAD_CONST              14 (182)
           6936 LOAD_CONST              47 (102)
           6939 LOAD_CONST              84 (111)
           6942 LOAD_CONST              17 (210)
           6945 LOAD_CONST              79 (151)
           6948 LOAD_CONST             239 (163)
           6951 LOAD_CONST             166 (243)
           6954 LOAD_CONST             237 (41)
           6957 LOAD_CONST              48 (34)
           6960 LOAD_CONST              22 (201)
           6963 LOAD_CONST             130 (40)
           6966 LOAD_CONST             111 (186)
           6969 LOAD_CONST              25 (189)
           6972 LOAD_CONST              93 (176)
           6975 LOAD_CONST              26 (70)
           6978 LOAD_CONST              27 (203)
           6981 LOAD_CONST             186 (234)
           6984 LOAD_CONST              50 (141)
           6987 LOAD_CONST              30 (126)
           6990 LOAD_CONST              32 (209)
           6993 LOAD_CONST             187 (160)
           6996 LOAD_CONST             180 (200)
           6999 LOAD_CONST             163 (13)
           7002 LOAD_CONST             155 (94)
           7005 LOAD_CONST             121 (36)
           7008 LOAD_CONST             122 (132)
           7011 LOAD_CONST             156 (202)
           7014 LOAD_CONST              23 (207)
           7017 LOAD_CONST              57 (129)
           7020 LOAD_CONST              32 (209)
           7023 LOAD_CONST             170 (195)
           7026 LOAD_CONST              22 (201)
           7029 LOAD_CONST             244 (212)
           7032 LOAD_CONST             102 (231)
           7035 LOAD_CONST             105 (113)
           7038 LOAD_CONST              46 (255)
           7041 LOAD_CONST              67 (229)
           7044 LOAD_CONST             235 (71)
           7047 LOAD_CONST             245 (89)
           7050 LOAD_CONST             160 (154)
           7053 LOAD_CONST             130 (40)
           7056 LOAD_CONST             246 (236)
           7059 LOAD_CONST              53 (228)
           7062 LOAD_CONST               3 (43)
           7065 LOAD_CONST             180 (200)
           7068 LOAD_CONST             158 (226)
           7071 LOAD_CONST              89 (134)
           7074 LOAD_CONST             177 (253)
           7077 LOAD_CONST               8 (57)
           7080 LOAD_CONST             212 (20)
           7083 LOAD_CONST             225 (125)
           7086 LOAD_CONST             192 (156)
           7089 LOAD_CONST              30 (126)
           7092 LOAD_CONST             209 (235)
           7095 LOAD_CONST             145 (121)
           7098 LOAD_CONST             171 (8)
           7101 LOAD_CONST              66 (14)
           7104 LOAD_CONST             213 (124)
           7107 LOAD_CONST             108 (214)
           7110 LOAD_CONST             102 (231)
           7113 LOAD_CONST             142 (116)
           7116 LOAD_CONST             189 (230)
           7119 LOAD_CONST              77 (90)
           7122 LOAD_CONST             113 (147)
           7125 LOAD_CONST              69 (146)
           7128 LOAD_CONST             180 (200)
           7131 LOAD_CONST             104 (149)
           7134 LOAD_CONST             145 (121)
           7137 LOAD_CONST              72 (194)
           7140 LOAD_CONST             186 (234)
           7143 LOAD_CONST              65 (4)
           7146 LOAD_CONST              74 (178)
           7149 LOAD_CONST             192 (156)
           7152 LOAD_CONST             146 (29)
           7155 LOAD_CONST              77 (90)
           7158 LOAD_CONST             240 (185)
           7161 LOAD_CONST             213 (124)
           7164 LOAD_CONST              79 (151)
           7167 LOAD_CONST             156 (202)
           7170 LOAD_CONST              36 (64)
           7173 LOAD_CONST              20 (87)
           7176 LOAD_CONST             120 (86)
           7179 LOAD_CONST             109 (119)
           7182 LOAD_CONST             137 (173)
           7185 LOAD_CONST              37 (225)
           7188 LOAD_CONST             157 (95)
           7191 LOAD_CONST             110 (22)
           7194 LOAD_CONST             251 (66)
           7197 LOAD_CONST              14 (182)
           7200 LOAD_CONST              17 (210)
           7203 LOAD_CONST              20 (87)
           7206 LOAD_CONST              18 (227)
           7209 LOAD_CONST              29 (140)
           7212 LOAD_CONST             172 (37)
           7215 LOAD_CONST             230 (249)
           7218 LOAD_CONST             131 (198)
           7221 LOAD_CONST              92 (150)
           7224 LOAD_CONST              33 (219)
           7227 LOAD_CONST              14 (182)
           7230 LOAD_CONST              94 (76)
           7233 LOAD_CONST              16 (110)
           7236 LOAD_CONST              16 (110)
           7239 LOAD_CONST             145 (121)
           7242 LOAD_CONST             200 (93)
           7245 LOAD_CONST             147 (221)
           7248 LOAD_CONST             100 (240)
           7251 LOAD_CONST              79 (151)
           7254 LOAD_CONST             230 (249)
           7257 LOAD_CONST             210 (142)
           7260 LOAD_CONST              97 (222)
           7263 LOAD_CONST             168 (46)
           7266 LOAD_CONST              79 (151)
           7269 LOAD_CONST             219 (193)
           7272 LOAD_CONST             193 (148)
           7275 LOAD_CONST             141 (97)
           7278 LOAD_CONST              78 (117)
           7281 LOAD_CONST             106 (85)
           7284 LOAD_CONST             169 (11)
           7287 LOAD_CONST             204 (197)
           7290 LOAD_CONST             108 (214)
           7293 LOAD_CONST              23 (207)
           7296 LOAD_CONST             213 (124)
           7299 LOAD_CONST              65 (4)
           7302 LOAD_CONST             184 (31)
           7305 LOAD_CONST             164 (246)
           7308 LOAD_CONST              82 (68)
           7311 LOAD_CONST              73 (242)
           7314 LOAD_CONST             195 (104)
           7317 LOAD_CONST              71 (120)
           7320 LOAD_CONST             131 (198)
           7323 LOAD_CONST              91 (199)
           7326 LOAD_CONST              44 (155)
           7329 LOAD_CONST              84 (111)
           7332 LOAD_CONST              60 (101)
           7335 LOAD_CONST              98 (252)
           7338 LOAD_CONST              25 (189)
           7341 LOAD_CONST              73 (242)
           7344 LOAD_CONST             162 (177)
           7347 LOAD_CONST             251 (66)
           7350 LOAD_CONST             152 (106)
           7353 LOAD_CONST             250 (78)
           7356 LOAD_CONST             108 (214)
           7359 LOAD_CONST             223 (61)
           7362 LOAD_CONST             188 (52)
           7365 LOAD_CONST             230 (249)
           7368 LOAD_CONST             234 (137)
           7371 LOAD_CONST             123 (56)
           7374 LOAD_CONST             117 (190)
           7377 LOAD_CONST              47 (102)
           7380 LOAD_CONST             209 (235)
           7383 LOAD_CONST              60 (101)
           7386 LOAD_CONST              79 (151)
           7389 LOAD_CONST             127 (162)
           7392 LOAD_CONST              87 (51)
           7395 LOAD_CONST              71 (120)
           7398 LOAD_CONST             238 (1)
           7401 LOAD_CONST              16 (110)
           7404 LOAD_CONST              26 (70)
           7407 LOAD_CONST              40 (208)
           7410 LOAD_CONST             129 (100)
           7413 LOAD_CONST             140 (49)
           7416 LOAD_CONST             127 (162)
           7419 LOAD_CONST             222 (159)
           7422 LOAD_CONST              89 (134)
           7425 LOAD_CONST              17 (210)
           7428 LOAD_CONST              98 (252)
           7431 LOAD_CONST             133 (114)
           7434 LOAD_CONST              24 (187)
           7437 LOAD_CONST              24 (187)
           7440 LOAD_CONST             157 (95)
           7443 LOAD_CONST              11 (73)
           7446 LOAD_CONST              27 (203)
           7449 LOAD_CONST             107 (19)
           7452 LOAD_CONST             120 (86)
           7455 LOAD_CONST              47 (102)
           7458 LOAD_CONST             163 (13)
           7461 LOAD_CONST             164 (246)
           7464 LOAD_CONST             185 (172)
           7467 LOAD_CONST              40 (208)
           7470 LOAD_CONST             236 (152)
           7473 LOAD_CONST             111 (186)
           7476 LOAD_CONST             174 (168)
           7479 LOAD_CONST             247 (65)
           7482 LOAD_CONST              50 (141)
           7485 LOAD_CONST             151 (6)
           7488 LOAD_CONST             193 (148)
           7491 LOAD_CONST              48 (34)
           7494 LOAD_CONST              75 (115)
           7497 LOAD_CONST             114 (27)
           7500 LOAD_CONST             169 (11)
           7503 LOAD_CONST               7 (10)
           7506 LOAD_CONST             147 (221)
           7509 LOAD_CONST             112 (165)
           7512 LOAD_CONST               8 (57)
           7515 LOAD_CONST             147 (221)
           7518 LOAD_CONST             240 (185)
           7521 LOAD_CONST              66 (14)
           7524 LOAD_CONST              63 (17)
           7527 LOAD_CONST             220 (60)
           7530 LOAD_CONST             151 (6)
           7533 LOAD_CONST             212 (20)
           7536 LOAD_CONST             150 (247)
           7539 LOAD_CONST               2 (48)
           7542 LOAD_CONST             238 (1)
           7545 LOAD_CONST              13 (96)
           7548 LOAD_CONST              91 (199)
           7551 LOAD_CONST             204 (197)
           7554 LOAD_CONST              74 (178)
           7557 LOAD_CONST             217 (26)
           7560 LOAD_CONST              18 (227)
           7563 LOAD_CONST              55 (224)
           7566 LOAD_CONST               2 (48)
           7569 LOAD_CONST             107 (19)
           7572 LOAD_CONST              75 (115)
           7575 LOAD_CONST             125 (250)
           7578 LOAD_CONST             246 (236)
           7581 LOAD_CONST             240 (185)
           7584 LOAD_CONST             191 (180)
           7587 LOAD_CONST             132 (184)
           7590 LOAD_CONST              66 (14)
           7593 LOAD_CONST             173 (131)
           7596 LOAD_CONST              25 (189)
           7599 LOAD_CONST             154 (143)
           7602 LOAD_CONST              42 (144)
           7605 LOAD_CONST              49 (91)
           7608 LOAD_CONST              48 (34)
           7611 LOAD_CONST             131 (198)
           7614 LOAD_CONST             151 (6)
           7617 LOAD_CONST              76 (25)
           7620 LOAD_CONST              87 (51)
           7623 LOAD_CONST             179 (109)
           7626 LOAD_CONST             166 (243)
           7629 LOAD_CONST              44 (155)
           7632 LOAD_CONST             177 (253)
           7635 LOAD_CONST             122 (132)
           7638 LOAD_CONST              17 (210)
           7641 LOAD_CONST              34 (105)
           7644 LOAD_CONST             186 (234)
           7647 LOAD_CONST              78 (117)
           7650 LOAD_CONST              93 (176)
           7653 LOAD_CONST             210 (142)
           7656 LOAD_CONST             229 (77)
           7659 LOAD_CONST             206 (44)
           7662 LOAD_CONST              77 (90)
           7665 LOAD_CONST             251 (66)
           7668 LOAD_CONST             199 (136)
           7671 LOAD_CONST             166 (243)
           7674 LOAD_CONST             162 (177)
           7677 LOAD_CONST             205 (42)
           7680 LOAD_CONST              19 (7)
           7683 LOAD_CONST             170 (195)
           7686 LOAD_CONST             195 (104)
           7689 LOAD_CONST              51 (32)
           7692 LOAD_CONST             201 (47)
           7695 LOAD_CONST              66 (14)
           7698 LOAD_CONST             257 (158)
           7701 LOAD_CONST             233 (118)
           7704 LOAD_CONST             235 (71)
           7707 LOAD_CONST             190 (232)
           7710 LOAD_CONST              57 (129)
           7713 LOAD_CONST               5 (211)
           7716 LOAD_CONST              92 (150)
           7719 LOAD_CONST             188 (52)
           7722 LOAD_CONST             229 (77)
           7725 LOAD_CONST             170 (195)
           7728 LOAD_CONST             127 (162)
           7731 LOAD_CONST              17 (210)
           7734 LOAD_CONST              33 (219)
           7737 LOAD_CONST             107 (19)
           7740 LOAD_CONST             135 (45)
           7743 LOAD_CONST             209 (235)
           7746 LOAD_CONST              20 (87)
           7749 LOAD_CONST             162 (177)
           7752 LOAD_CONST             155 (94)
           7755 LOAD_CONST             255 (188)
           7758 LOAD_CONST             191 (180)
           7761 LOAD_CONST             183 (181)
           7764 LOAD_CONST             172 (37)
           7767 LOAD_CONST              64 (98)
           7770 LOAD_CONST              34 (105)
           7773 LOAD_CONST             178 (191)
           7776 LOAD_CONST             187 (160)
           7779 LOAD_CONST              88 (139)
           7782 LOAD_CONST             117 (190)
           7785 LOAD_CONST             159 (241)
           7788 LOAD_CONST             138 (153)
           7791 LOAD_CONST             218 (192)
           7794 LOAD_CONST             147 (221)
           7797 LOAD_CONST               9 (254)
           7800 LOAD_CONST             165 (83)
           7803 LOAD_CONST             244 (212)
           7806 LOAD_CONST              49 (91)
           7809 LOAD_CONST              47 (102)
           7812 LOAD_CONST             203 (58)
           7815 LOAD_CONST              67 (229)
           7818 LOAD_CONST             118 (62)
           7821 LOAD_CONST              91 (199)
           7824 LOAD_CONST              99 (128)
           7827 LOAD_CONST             226 (103)
           7830 LOAD_CONST              56 (220)
           7833 LOAD_CONST              25 (189)
           7836 LOAD_CONST               6 (216)
           7839 LOAD_CONST               4 (238)
           7842 LOAD_CONST             215 (67)
           7845 LOAD_CONST              30 (126)
           7848 LOAD_CONST             198 (92)
           7851 LOAD_CONST             191 (180)
           7854 LOAD_CONST             142 (116)
           7857 LOAD_CONST             256 (166)
           7860 LOAD_CONST             229 (77)
           7863 LOAD_CONST             140 (49)
           7866 LOAD_CONST             172 (37)
           7869 LOAD_CONST             220 (60)
           7872 LOAD_CONST              73 (242)
           7875 LOAD_CONST             108 (214)
           7878 LOAD_CONST             207 (2)
           7881 LOAD_CONST             246 (236)
           7884 LOAD_CONST               2 (48)
           7887 LOAD_CONST             242 (217)
           7890 LOAD_CONST             240 (185)
           7893 LOAD_CONST             196 (245)
           7896 LOAD_CONST             219 (193)
           7899 LOAD_CONST              11 (73)
           7902 LOAD_CONST             180 (200)
           7905 LOAD_CONST             166 (243)
           7908 LOAD_CONST              71 (120)
           7911 LOAD_CONST             115 (215)
           7914 LOAD_CONST             213 (124)
           7917 LOAD_CONST             188 (52)
           7920 LOAD_CONST             136 (55)
           7923 LOAD_CONST              49 (91)
           7926 LOAD_CONST             224 (15)
           7929 LOAD_CONST              53 (228)
           7932 LOAD_CONST             239 (163)
           7935 LOAD_CONST             248 (80)
           7938 LOAD_CONST              84 (111)
           7941 LOAD_CONST              71 (120)
           7944 LOAD_CONST              94 (76)
           7947 LOAD_CONST             256 (166)
           7950 LOAD_CONST             122 (132)
           7953 LOAD_CONST              83 (59)
           7956 LOAD_CONST              76 (25)
           7959 LOAD_CONST             195 (104)
           7962 LOAD_CONST               5 (211)
           7965 LOAD_CONST             246 (236)
           7968 LOAD_CONST             217 (26)
           7971 LOAD_CONST             104 (149)
           7974 LOAD_CONST             122 (132)
           7977 LOAD_CONST              90 (50)
           7980 LOAD_CONST              61 (157)
           7983 LOAD_CONST             103 (196)
           7986 LOAD_CONST             211 (170)
           7989 LOAD_CONST              72 (194)
           7992 LOAD_CONST             108 (214)
           7995 LOAD_CONST             118 (62)
           7998 LOAD_CONST             232 (123)
           8001 LOAD_CONST             146 (29)
           8004 LOAD_CONST             163 (13)
           8007 LOAD_CONST              55 (224)
           8010 LOAD_CONST             210 (142)
           8013 LOAD_CONST              18 (227)
           8016 LOAD_CONST              99 (128)
           8019 LOAD_CONST              61 (157)
           8022 LOAD_CONST             199 (136)
           8025 LOAD_CONST             164 (246)
           8028 LOAD_CONST             118 (62)
           8031 LOAD_CONST             186 (234)
           8034 LOAD_CONST             103 (196)
           8037 LOAD_CONST             193 (148)
           8040 LOAD_CONST             141 (97)
           8043 LOAD_CONST             109 (119)
           8046 LOAD_CONST             106 (85)
           8049 LOAD_CONST             109 (119)
           8052 LOAD_CONST             218 (192)
           8055 LOAD_CONST             161 (183)
           8058 LOAD_CONST              33 (219)
           8061 LOAD_CONST             169 (11)
           8064 LOAD_CONST             141 (97)
           8067 LOAD_CONST              59 (21)
           8070 LOAD_CONST             160 (154)
           8073 LOAD_CONST               2 (48)
           8076 LOAD_CONST             133 (114)
           8079 LOAD_CONST             182 (107)
           8082 LOAD_CONST              71 (120)
           8085 LOAD_CONST              24 (187)
           8088 LOAD_CONST              74 (178)
           8091 LOAD_CONST              39 (239)
           8094 LOAD_CONST              34 (105)
           8097 LOAD_CONST              90 (50)
           8100 LOAD_CONST              67 (229)
           8103 LOAD_CONST             115 (215)
           8106 LOAD_CONST             241 (244)
           8109 LOAD_CONST             162 (177)
           8112 LOAD_CONST              12 (74)
           8115 LOAD_CONST             195 (104)
           8118 LOAD_CONST             250 (78)
           8121 LOAD_CONST             106 (85)
           8124 LOAD_CONST             220 (60)
           8127 LOAD_CONST             155 (94)
           8130 LOAD_CONST             209 (235)
           8133 LOAD_CONST              55 (224)
           8136 LOAD_CONST             120 (86)
           8139 LOAD_CONST              42 (144)
           8142 LOAD_CONST              47 (102)
           8145 LOAD_CONST             209 (235)
           8148 LOAD_CONST             126 (54)
           8151 LOAD_CONST             178 (191)
           8154 LOAD_CONST             216 (223)
           8157 LOAD_CONST             188 (52)
           8160 LOAD_CONST              71 (120)
           8163 LOAD_CONST             238 (1)
           8166 LOAD_CONST              51 (32)
           8169 LOAD_CONST             157 (95)
           8172 LOAD_CONST              93 (176)
           8175 LOAD_CONST             110 (22)
           8178 LOAD_CONST             251 (66)
           8181 LOAD_CONST             156 (202)
           8184 LOAD_CONST             112 (165)
           8187 LOAD_CONST             257 (158)
           8190 LOAD_CONST             253 (167)
           8193 LOAD_CONST             230 (249)
           8196 LOAD_CONST             133 (114)
           8199 LOAD_CONST              24 (187)
           8202 LOAD_CONST              79 (151)
           8205 LOAD_CONST             119 (79)
           8208 LOAD_CONST             223 (61)
           8211 LOAD_CONST             256 (166)
           8214 LOAD_CONST             101 (99)
           8217 LOAD_CONST             172 (37)
           8220 LOAD_CONST             107 (19)
           8223 LOAD_CONST             145 (121)
           8226 LOAD_CONST              67 (229)
           8229 LOAD_CONST             185 (172)
           8232 LOAD_CONST              40 (208)
           8235 LOAD_CONST             156 (202)
           8238 LOAD_CONST              22 (201)
           8241 LOAD_CONST             204 (197)
           8244 LOAD_CONST             140 (49)
           8247 LOAD_CONST             158 (226)
           8250 LOAD_CONST              21 (38)
           8253 LOAD_CONST             128 (251)
           8256 LOAD_CONST             207 (2)
           8259 LOAD_CONST             167 (30)
           8262 LOAD_CONST             144 (122)
           8265 LOAD_CONST               3 (43)
           8268 LOAD_CONST             143 (112)
           8271 LOAD_CONST             183 (181)
           8274 LOAD_CONST             103 (196)
           8277 LOAD_CONST             106 (85)
           8280 LOAD_CONST             239 (163)
           8283 LOAD_CONST              56 (220)
           8286 LOAD_CONST             168 (46)
           8289 LOAD_CONST             206 (44)
           8292 LOAD_CONST             148 (28)
           8295 LOAD_CONST             118 (62)
           8298 LOAD_CONST              54 (81)
           8301 LOAD_CONST              98 (252)
           8304 LOAD_CONST               2 (48)
           8307 LOAD_CONST             238 (1)
           8310 LOAD_CONST             152 (106)
           8313 LOAD_CONST             108 (214)
           8316 LOAD_CONST              53 (228)
           8319 LOAD_CONST             154 (143)
           8322 LOAD_CONST             203 (58)
           8325 LOAD_CONST             103 (196)
           8328 LOAD_CONST             191 (180)
           8331 LOAD_CONST             250 (78)
           8334 LOAD_CONST             232 (123)
           8337 LOAD_CONST             157 (95)
           8340 LOAD_CONST              42 (144)
           8343 LOAD_CONST              86 (204)
           8346 LOAD_CONST             102 (231)
           8349 LOAD_CONST             255 (188)
           8352 LOAD_CONST             199 (136)
           8355 LOAD_CONST              48 (34)
           8358 LOAD_CONST             249 (179)
           8361 LOAD_CONST             161 (183)
           8364 LOAD_CONST              86 (204)
           8367 LOAD_CONST              93 (176)
           8370 LOAD_CONST              47 (102)
           8373 LOAD_CONST             207 (2)
           8376 LOAD_CONST              61 (157)
           8379 LOAD_CONST             151 (6)
           8382 LOAD_CONST             101 (99)
           8385 LOAD_CONST              87 (51)
           8388 LOAD_CONST             179 (109)
           8391 LOAD_CONST             166 (243)
           8394 LOAD_CONST             125 (250)
           8397 LOAD_CONST             122 (132)
           8400 LOAD_CONST              42 (144)
           8403 LOAD_CONST             180 (200)
           8406 LOAD_CONST              34 (105)
           8409 LOAD_CONST             164 (246)
           8412 LOAD_CONST             129 (100)
           8415 LOAD_CONST             116 (174)
           8418 LOAD_CONST              27 (203)
           8421 LOAD_CONST              75 (115)
           8424 LOAD_CONST              21 (38)
           8427 LOAD_CONST             165 (83)
           8430 LOAD_CONST               3 (43)
           8433 LOAD_CONST              88 (139)
           8436 LOAD_CONST              25 (189)
           8439 LOAD_CONST              24 (187)
           8442 LOAD_CONST             203 (58)
           8445 LOAD_CONST              19 (7)
           8448 LOAD_CONST               9 (254)
           8451 LOAD_CONST              10 (72)
           8454 LOAD_CONST              94 (76)
           8457 LOAD_CONST               8 (57)
           8460 LOAD_CONST              71 (120)
           8463 LOAD_CONST              14 (182)
           8466 LOAD_CONST              95 (18)
           8469 LOAD_CONST              16 (110)
           8472 LOAD_CONST              17 (210)
           8475 LOAD_CONST             158 (226)
           8478 LOAD_CONST             253 (167)
           8481 LOAD_CONST              73 (242)
           8484 LOAD_CONST             165 (83)
           8487 LOAD_CONST              62 (39)
           8490 LOAD_CONST             103 (196)
           8493 LOAD_CONST              38 (171)
           8496 LOAD_CONST             256 (166)
           8499 LOAD_CONST             255 (188)
           8502 LOAD_CONST             121 (36)
           8505 LOAD_CONST              26 (70)
           8508 LOAD_CONST             131 (198)
           8511 LOAD_CONST              34 (105)
           8514 LOAD_CONST              44 (155)
           8517 LOAD_CONST             232 (123)
           8520 LOAD_CONST             180 (200)
           8523 LOAD_CONST             108 (214)
           8526 LOAD_CONST              56 (220)
           8529 LOAD_CONST             124 (12)
           8532 LOAD_CONST             114 (27)
           8535 LOAD_CONST             247 (65)
           8538 LOAD_CONST              31 (138)
           8541 LOAD_CONST              27 (203)
           8544 LOAD_CONST             230 (249)
           8547 LOAD_CONST             222 (159)
           8550 LOAD_CONST              32 (209)
           8553 LOAD_CONST              41 (169)
           8556 LOAD_CONST             156 (202)
           8559 LOAD_CONST              89 (134)
           8562 LOAD_CONST              80 (145)
           8565 LOAD_CONST              75 (115)
           8568 LOAD_CONST              46 (255)
           8571 LOAD_CONST              47 (102)
           8574 LOAD_CONST             254 (53)
           8577 LOAD_CONST             232 (123)
           8580 LOAD_CONST              50 (141)
           8583 LOAD_CONST              94 (76)
           8586 LOAD_CONST              39 (239)
           8589 LOAD_CONST              50 (141)
           8592 LOAD_CONST              54 (81)
           8595 LOAD_CONST             204 (197)
           8598 LOAD_CONST             154 (143)
           8601 LOAD_CONST             241 (244)
           8604 LOAD_CONST             159 (241)
           8607 LOAD_CONST             123 (56)
           8610 LOAD_CONST             145 (121)
           8613 LOAD_CONST              13 (96)
           8616 LOAD_CONST              39 (239)
           8619 LOAD_CONST             163 (13)
           8622 LOAD_CONST              91 (199)
           8625 LOAD_CONST             202 (69)
           8628 LOAD_CONST             225 (125)
           8631 LOAD_CONST             254 (53)
           8634 LOAD_CONST             129 (100)
           8637 LOAD_CONST             211 (170)
           8640 LOAD_CONST             221 (130)
           8643 LOAD_CONST             182 (107)
           8646 LOAD_CONST             139 (205)
           8649 LOAD_CONST             136 (55)
           8652 LOAD_CONST             236 (152)
           8655 LOAD_CONST              55 (224)
           8658 LOAD_CONST              24 (187)
           8661 LOAD_CONST             234 (137)
           8664 LOAD_CONST              76 (25)
           8667 LOAD_CONST             116 (174)
           8670 LOAD_CONST             132 (184)
           8673 LOAD_CONST             194 (108)
           8676 LOAD_CONST             147 (221)
           8679 LOAD_CONST              30 (126)
           8682 LOAD_CONST              71 (120)
           8685 LOAD_CONST             237 (41)
           8688 LOAD_CONST              95 (18)
           8691 LOAD_CONST              66 (14)
           8694 LOAD_CONST             104 (149)
           8697 LOAD_CONST              27 (203)
           8700 LOAD_CONST             140 (49)
           8703 LOAD_CONST              81 (3)
           8706 LOAD_CONST              96 (127)
           8709 LOAD_CONST              35 (9)
           8712 LOAD_CONST              44 (155)
           8715 LOAD_CONST              86 (204)
           8718 LOAD_CONST             157 (95)
           8721 LOAD_CONST             152 (106)
           8724 LOAD_CONST              36 (64)
           8727 LOAD_CONST              53 (228)
           8730 LOAD_CONST               5 (211)
           8733 LOAD_CONST              87 (51)
           8736 LOAD_CONST             189 (230)
           8739 LOAD_CONST              29 (140)
           8742 LOAD_CONST             247 (65)
           8745 LOAD_CONST              44 (155)
           8748 LOAD_CONST             103 (196)
           8751 LOAD_CONST              92 (150)
           8754 LOAD_CONST             162 (177)
           8757 LOAD_CONST              40 (208)
           8760 LOAD_CONST              48 (34)
           8763 LOAD_CONST             105 (113)
           8766 LOAD_CONST             215 (67)
           8769 LOAD_CONST              35 (9)
           8772 LOAD_CONST             253 (167)
           8775 LOAD_CONST             175 (175)
           8778 LOAD_CONST               4 (238)
           8781 LOAD_CONST              99 (128)
           8784 LOAD_CONST              61 (157)
           8787 LOAD_CONST             199 (136)
           8790 LOAD_CONST              37 (225)
           8793 LOAD_CONST              54 (81)
           8796 LOAD_CONST             162 (177)
           8799 LOAD_CONST              74 (178)
           8802 LOAD_CONST              22 (201)
           8805 LOAD_CONST             254 (53)
           8808 LOAD_CONST              87 (51)
           8811 LOAD_CONST               2 (48)
           8814 LOAD_CONST              28 (5)
           8817 LOAD_CONST             174 (168)
           8820 LOAD_CONST             161 (183)
           8823 LOAD_CONST               6 (216)
           8826 LOAD_CONST              95 (18)
           8829 LOAD_CONST             195 (104)
           8832 LOAD_CONST              49 (91)
           8835 LOAD_CONST             113 (147)
           8838 LOAD_CONST             153 (33)
           8841 LOAD_CONST             148 (28)
           8844 LOAD_CONST              35 (9)
           8847 LOAD_CONST             163 (13)
           8850 LOAD_CONST              85 (218)
           8853 LOAD_CONST             183 (181)
           8856 LOAD_CONST              24 (187)
           8859 LOAD_CONST             225 (125)
           8862 LOAD_CONST              35 (9)
           8865 LOAD_CONST              42 (144)
           8868 LOAD_CONST              74 (178)
           8871 LOAD_CONST             244 (212)
           8874 LOAD_CONST             210 (142)
           8877 LOAD_CONST             200 (93)
           8880 LOAD_CONST             184 (31)
           8883 LOAD_CONST             200 (93)
           8886 LOAD_CONST             106 (85)
           8889 LOAD_CONST             220 (60)
           8892 LOAD_CONST             188 (52)
           8895 LOAD_CONST              24 (187)
           8898 LOAD_CONST              53 (228)
           8901 LOAD_CONST              96 (127)
           8904 LOAD_CONST             173 (131)
           8907 LOAD_CONST             153 (33)
           8910 LOAD_CONST             211 (170)
           8913 LOAD_CONST             144 (122)
           8916 LOAD_CONST             222 (159)
           8919 LOAD_CONST             131 (198)
           8922 LOAD_CONST             120 (86)
           8925 LOAD_CONST             238 (1)
           8928 LOAD_CONST             195 (104)
           8931 LOAD_CONST             229 (77)
           8934 LOAD_CONST             251 (66)
           8937 LOAD_CONST              93 (176)
           8940 LOAD_CONST               7 (10)
           8943 LOAD_CONST              63 (17)
           8946 LOAD_CONST              61 (157)
           8949 LOAD_CONST             253 (167)
           8952 LOAD_CONST              85 (218)
           8955 LOAD_CONST              40 (208)
           8958 LOAD_CONST              98 (252)
           8961 LOAD_CONST             133 (114)
           8964 LOAD_CONST              24 (187)
           8967 LOAD_CONST             204 (197)
           8970 LOAD_CONST             203 (58)
           8973 LOAD_CONST              10 (72)
           8976 LOAD_CONST              27 (203)
           8979 LOAD_CONST             107 (19)
           8982 LOAD_CONST              65 (4)
           8985 LOAD_CONST             254 (53)
           8988 LOAD_CONST              30 (126)
           8991 LOAD_CONST              67 (229)
           8994 LOAD_CONST             185 (172)
           8997 LOAD_CONST             221 (130)
           9000 LOAD_CONST              31 (138)
           9003 LOAD_CONST               5 (211)
           9006 LOAD_CONST             204 (197)
           9009 LOAD_CONST             140 (49)
           9012 LOAD_CONST             156 (202)
           9015 LOAD_CONST              54 (81)
           9018 LOAD_CONST              55 (224)
           9021 LOAD_CONST             207 (2)
           9024 LOAD_CONST             167 (30)
           9027 LOAD_CONST             130 (40)
           9030 LOAD_CONST             198 (92)
           9033 LOAD_CONST             145 (121)
           9036 LOAD_CONST             183 (181)
           9039 LOAD_CONST             103 (196)
           9042 LOAD_CONST             153 (33)
           9045 LOAD_CONST             216 (223)
           9048 LOAD_CONST             147 (221)
           9051 LOAD_CONST             168 (46)
           9054 LOAD_CONST             206 (44)
           9057 LOAD_CONST             194 (108)
           9060 LOAD_CONST              76 (25)
           9063 LOAD_CONST              64 (98)
           9066 LOAD_CONST             173 (131)
           9069 LOAD_CONST             120 (86)
           9072 LOAD_CONST              16 (110)
           9075 LOAD_CONST              58 (24)
           9078 LOAD_CONST              23 (207)
           9081 LOAD_CONST              80 (145)
           9084 LOAD_CONST              70 (133)
           9087 LOAD_CONST             203 (58)
           9090 LOAD_CONST             103 (196)
           9093 LOAD_CONST              91 (199)
           9096 LOAD_CONST              12 (74)
           9099 LOAD_CONST              81 (3)
           9102 LOAD_CONST              68 (0)
           9105 LOAD_CONST             166 (243)
           9108 LOAD_CONST             239 (163)
           9111 LOAD_CONST             228 (233)
           9114 LOAD_CONST              53 (228)
           9117 LOAD_CONST              37 (225)
           9120 LOAD_CONST             250 (78)
           9123 LOAD_CONST             108 (214)
           9126 LOAD_CONST              67 (229)
           9129 LOAD_CONST              53 (228)
           9132 LOAD_CONST              93 (176)
           9135 LOAD_CONST              47 (102)
           9138 LOAD_CONST             207 (2)
           9141 LOAD_CONST             228 (233)
           9144 LOAD_CONST             233 (118)
           9147 LOAD_CONST             182 (107)
           9150 LOAD_CONST              87 (51)
           9153 LOAD_CONST             179 (109)
           9156 LOAD_CONST              42 (144)
           9159 LOAD_CONST              41 (169)
           9162 LOAD_CONST             160 (154)
           9165 LOAD_CONST             176 (135)
           9168 LOAD_CONST             240 (185)
           9171 LOAD_CONST              68 (0)
           9174 LOAD_CONST              89 (134)
           9177 LOAD_CONST             149 (16)
           9180 LOAD_CONST              18 (227)
           9183 LOAD_CONST             131 (198)
           9186 LOAD_CONST              65 (4)
           9189 LOAD_CONST             142 (116)
           9192 LOAD_CONST              15 (82)
           9195 LOAD_CONST               3 (43)
           9198 LOAD_CONST               4 (238)
           9201 LOAD_CONST               5 (211)
           9204 LOAD_CONST             185 (172)
           9207 LOAD_CONST             169 (11)
           9210 LOAD_CONST               8 (57)
           9213 LOAD_CONST               9 (254)
           9216 LOAD_CONST              10 (72)
           9219 LOAD_CONST             171 (8)
           9222 LOAD_CONST              58 (24)
           9225 LOAD_CONST              64 (98)
           9228 LOAD_CONST              14 (182)
           9231 LOAD_CONST              95 (18)
           9234 LOAD_CONST              16 (110)
           9237 LOAD_CONST             256 (166)
           9240 LOAD_CONST              67 (229)
           9243 LOAD_CONST             227 (161)
           9246 LOAD_CONST             166 (243)
           9249 LOAD_CONST             106 (85)
           9252 LOAD_CONST             208 (84)
           9255 LOAD_CONST             174 (168)
           9258 LOAD_CONST             204 (197)
           9261 LOAD_CONST             216 (223)
           9264 LOAD_CONST              17 (210)
           9267 LOAD_CONST             155 (94)
           9270 LOAD_CONST              59 (21)
           9273 LOAD_CONST             180 (200)
           9276 LOAD_CONST              34 (105)
           9279 LOAD_CONST              29 (140)
           9282 LOAD_CONST              30 (126)
           9285 LOAD_CONST             221 (130)
           9288 LOAD_CONST             204 (197)
           9291 LOAD_CONST              33 (219)
           9294 LOAD_CONST             163 (13)
           9297 LOAD_CONST              35 (9)
           9300 LOAD_CONST             188 (52)
           9303 LOAD_CONST             176 (135)
           9306 LOAD_CONST             156 (202)
           9309 LOAD_CONST              38 (171)
           9312 LOAD_CONST             173 (131)
           9315 LOAD_CONST             117 (190)
           9318 LOAD_CONST              85 (218)
           9321 LOAD_CONST             236 (152)
           9324 LOAD_CONST              40 (208)
           9327 LOAD_CONST              44 (155)
           9330 LOAD_CONST              75 (115)
           9333 LOAD_CONST              46 (255)
           9336 LOAD_CONST             188 (52)
           9339 LOAD_CONST             215 (67)
           9342 LOAD_CONST             245 (89)
           9345 LOAD_CONST              50 (141)
           9348 LOAD_CONST              94 (76)
           9351 LOAD_CONST              25 (189)
           9354 LOAD_CONST             190 (232)
           9357 LOAD_CONST             220 (60)
           9360 LOAD_CONST             183 (181)
           9363 LOAD_CONST              55 (224)
           9366 LOAD_CONST              73 (242)
           9369 LOAD_CONST              88 (139)
           9372 LOAD_CONST              58 (24)
           9375 LOAD_CONST             212 (20)
           9378 LOAD_CONST             238 (1)
           9381 LOAD_CONST              52 (237)
           9384 LOAD_CONST              19 (7)
           9387 LOAD_CONST              33 (219)
           9390 LOAD_CONST              94 (76)
           9393 LOAD_CONST              30 (126)
           9396 LOAD_CONST              13 (96)
           9399 LOAD_CONST             155 (94)
           9402 LOAD_CONST             231 (164)
           9405 LOAD_CONST             221 (130)
           9408 LOAD_CONST             144 (122)
           9411 LOAD_CONST              92 (150)
           9414 LOAD_CONST              87 (51)
           9417 LOAD_CONST              92 (150)
           9420 LOAD_CONST              98 (252)
           9423 LOAD_CONST             255 (188)
           9426 LOAD_CONST              53 (228)
           9429 LOAD_CONST              71 (120)
           9432 LOAD_CONST              72 (194)
           9435 LOAD_CONST              92 (150)
           9438 LOAD_CONST              75 (115)
           9441 LOAD_CONST              72 (194)
           9444 LOAD_CONST              75 (115)
           9447 LOAD_CONST              78 (117)
           9450 LOAD_CONST             168 (46)
           9453 LOAD_CONST             195 (104)
           9456 LOAD_CONST             133 (114)
           9459 LOAD_CONST              79 (151)
           9462 LOAD_CONST              27 (203)
           9465 LOAD_CONST             140 (49)
           9468 LOAD_CONST              54 (81)
           9471 LOAD_CONST             247 (65)
           9474 LOAD_CONST              51 (32)
           9477 LOAD_CONST              22 (201)
           9480 LOAD_CONST              67 (229)
           9483 LOAD_CONST               3 (43)
           9486 LOAD_CONST              16 (110)
           9489 LOAD_CONST              36 (64)
           9492 LOAD_CONST              14 (182)
           9495 LOAD_CONST             204 (197)
           9498 LOAD_CONST             198 (92)
           9501 LOAD_CONST              92 (150)
           9504 LOAD_CONST             228 (233)
           9507 LOAD_CONST             198 (92)
           9510 LOAD_CONST             228 (233)
           9513 LOAD_CONST             218 (192)
           9516 LOAD_CONST              92 (150)
           9519 LOAD_CONST             162 (177)
           9522 LOAD_CONST             183 (181)
           9525 LOAD_CONST             118 (62)
           9528 LOAD_CONST             109 (119)
           9531 LOAD_CONST             124 (12)
           9534 LOAD_CONST             146 (29)
           9537 LOAD_CONST              29 (140)
           9540 LOAD_CONST             241 (244)
           9543 LOAD_CONST             100 (240)
           9546 LOAD_CONST              99 (128)
           9549 LOAD_CONST              61 (157)
           9552 LOAD_CONST              85 (218)
           9555 LOAD_CONST             150 (247)
           9558 LOAD_CONST               8 (57)
           9561 LOAD_CONST             186 (234)
           9564 LOAD_CONST             103 (196)
           9567 LOAD_CONST             131 (198)
           9570 LOAD_CONST              87 (51)
           9573 LOAD_CONST             105 (113)
           9576 LOAD_CONST             106 (85)
           9579 LOAD_CONST             109 (119)
           9582 LOAD_CONST              69 (146)
           9585 LOAD_CONST              86 (204)
           9588 LOAD_CONST              38 (171)
           9591 LOAD_CONST             232 (123)
           9594 LOAD_CONST              65 (4)
           9597 LOAD_CONST             237 (41)
           9600 LOAD_CONST               4 (238)
           9603 LOAD_CONST              82 (68)
           9606 LOAD_CONST             105 (113)
           9609 LOAD_CONST             182 (107)
           9612 LOAD_CONST             205 (42)
           9615 LOAD_CONST             187 (160)
           9618 LOAD_CONST             219 (193)
           9621 LOAD_CONST              44 (155)
           9624 LOAD_CONST             114 (27)
           9627 LOAD_CONST             212 (20)
           9630 LOAD_CONST             230 (249)
           9633 LOAD_CONST             115 (215)
           9636 LOAD_CONST             241 (244)
           9639 LOAD_CONST             162 (177)
           9642 LOAD_CONST              94 (76)
           9645 LOAD_CONST             163 (13)
           9648 LOAD_CONST              51 (32)
           9651 LOAD_CONST              90 (50)
           9654 LOAD_CONST             245 (89)
           9657 LOAD_CONST              47 (102)
           9660 LOAD_CONST             154 (143)
           9663 LOAD_CONST             234 (137)
           9666 LOAD_CONST             123 (56)
           9669 LOAD_CONST              72 (194)
           9672 LOAD_CONST             188 (52)
           9675 LOAD_CONST              22 (201)
           9678 LOAD_CONST             126 (54)
           9681 LOAD_CONST             178 (191)
           9684 LOAD_CONST              38 (171)
           9687 LOAD_CONST             141 (97)
           9690 LOAD_CONST              47 (102)
           9693 LOAD_CONST             238 (1)
           9696 LOAD_CONST              51 (32)
           9699 LOAD_CONST              90 (50)
           9702 LOAD_CONST             173 (131)
           9705 LOAD_CONST             250 (78)
           9708 LOAD_CONST             140 (49)
           9711 LOAD_CONST             127 (162)
           9714 LOAD_CONST             103 (196)
           9717 LOAD_CONST              89 (134)
           9720 LOAD_CONST              40 (208)
           9723 LOAD_CONST              98 (252)
           9726 LOAD_CONST             133 (114)
           9729 LOAD_CONST              24 (187)
           9732 LOAD_CONST               9 (254)
           9735 LOAD_CONST             202 (69)
           9738 LOAD_CONST             220 (60)
           9741 LOAD_CONST             178 (191)
           9744 LOAD_CONST             110 (22)
           9747 LOAD_CONST             120 (86)
           9750 LOAD_CONST              83 (59)
           9753 LOAD_CONST              30 (126)
           9756 LOAD_CONST              69 (146)
           9759 LOAD_CONST              97 (222)
           9762 LOAD_CONST             240 (185)
           9765 LOAD_CONST             246 (236)
           9768 LOAD_CONST              14 (182)
           9771 LOAD_CONST             162 (177)
           9774 LOAD_CONST             254 (53)
           9777 LOAD_CONST             158 (226)
           9780 LOAD_CONST             142 (116)
           9783 LOAD_CONST              55 (224)
           9786 LOAD_CONST             143 (112)
           9789 LOAD_CONST             232 (123)
           9792 LOAD_CONST               7 (10)
           9795 LOAD_CONST             169 (11)
           9798 LOAD_CONST               3 (43)
           9801 LOAD_CONST              80 (145)
           9804 LOAD_CONST             103 (196)
           9807 LOAD_CONST             106 (85)
           9810 LOAD_CONST             115 (215)
           9813 LOAD_CONST             196 (245)
           9816 LOAD_CONST             168 (46)
           9819 LOAD_CONST             206 (44)
           9822 LOAD_CONST             148 (28)
           9825 LOAD_CONST              78 (117)
           9828 LOAD_CONST               3 (43)
           9831 LOAD_CONST             150 (247)
           9834 LOAD_CONST               2 (48)
           9837 LOAD_CONST             238 (1)
           9840 LOAD_CONST             152 (106)
           9843 LOAD_CONST              31 (138)
           9846 LOAD_CONST              67 (229)
           9849 LOAD_CONST             154 (143)
           9852 LOAD_CONST             203 (58)
           9855 LOAD_CONST             103 (196)
           9858 LOAD_CONST             191 (180)
           9861 LOAD_CONST              90 (50)
           9864 LOAD_CONST             144 (122)
           9867 LOAD_CONST             157 (95)
           9870 LOAD_CONST              42 (144)
           9873 LOAD_CONST             100 (240)
           9876 LOAD_CONST             150 (247)
           9879 LOAD_CONST             150 (247)
           9882 LOAD_CONST             125 (250)
           9885 LOAD_CONST             243 (75)
           9888 LOAD_CONST             170 (195)
           9891 LOAD_CONST             170 (195)
           9894 LOAD_CONST              85 (218)
           9897 LOAD_CONST             103 (196)
           9900 LOAD_CONST              16 (110)
           9903 LOAD_CONST             207 (2)
           9906 LOAD_CONST              61 (157)
           9909 LOAD_CONST              78 (117)
           9912 LOAD_CONST              20 (87)
           9915 LOAD_CONST             155 (94)
           9918 LOAD_CONST             207 (2)
           9921 LOAD_CONST              79 (151)
           9924 LOAD_CONST             249 (179)
           9927 LOAD_CONST              44 (155)
           9930 LOAD_CONST              92 (150)
           9933 LOAD_CONST             122 (132)
           9936 LOAD_CONST             238 (1)
           9939 LOAD_CONST              89 (134)
           9942 LOAD_CONST             149 (16)
           9945 LOAD_CONST              42 (144)
           9948 LOAD_CONST              86 (204)
           9951 LOAD_CONST              63 (17)
           9954 LOAD_CONST              21 (38)
           9957 LOAD_CONST             165 (83)
           9960 LOAD_CONST               3 (43)
           9963 LOAD_CONST             164 (246)
           9966 LOAD_CONST              17 (210)
           9969 LOAD_CONST             180 (200)
           9972 LOAD_CONST             169 (11)
           9975 LOAD_CONST             237 (41)
           9978 LOAD_CONST              46 (255)
           9981 LOAD_CONST             252 (88)
           9984 LOAD_CONST             229 (77)
           9987 LOAD_CONST              77 (90)
           9990 LOAD_CONST             141 (97)
           9993 LOAD_CONST             256 (166)
           9996 LOAD_CONST             107 (19)
           9999 LOAD_CONST              30 (126)
           10002 LOAD_CONST               5 (211)
           10005 LOAD_CONST             186 (234)
           10008 LOAD_CONST             256 (166)
           10011 LOAD_CONST             246 (236)
           10014 LOAD_CONST             208 (84)
           10017 LOAD_CONST             206 (44)
           10020 LOAD_CONST             180 (200)
           10023 LOAD_CONST             227 (161)
           10026 LOAD_CONST             111 (186)
           10029 LOAD_CONST             191 (180)
           10032 LOAD_CONST             126 (54)
           10035 LOAD_CONST             106 (85)
           10038 LOAD_CONST             156 (202)
           10041 LOAD_CONST              16 (110)
           10044 LOAD_CONST              50 (141)
           10047 LOAD_CONST             225 (125)
           10050 LOAD_CONST              43 (213)
           10053 LOAD_CONST             108 (214)
           10056 LOAD_CONST              85 (218)
           10059 LOAD_CONST              19 (7)
           10062 LOAD_CONST             171 (8)
           10065 LOAD_CONST             215 (67)
           10068 LOAD_CONST             122 (132)
           10071 LOAD_CONST             115 (215)
           10074 LOAD_CONST             211 (170)
           10077 LOAD_CONST              99 (128)
           10080 LOAD_CONST              40 (208)
           10083 LOAD_CONST             116 (174)
           10086 LOAD_CONST              27 (203)
           10089 LOAD_CONST             131 (198)
           10092 LOAD_CONST             160 (154)
           10095 LOAD_CONST              71 (120)
           10098 LOAD_CONST               9 (254)
           10101 LOAD_CONST             233 (118)
           10104 LOAD_CONST             235 (71)
           10107 LOAD_CONST             155 (94)
           10110 LOAD_CONST              29 (140)
           10113 LOAD_CONST             155 (94)
           10116 LOAD_CONST               4 (238)
           10119 LOAD_CONST               4 (238)
           10122 LOAD_CONST             223 (61)
           10125 LOAD_CONST              14 (182)
           10128 LOAD_CONST              37 (225)
           10131 LOAD_CONST              42 (144)
           10134 LOAD_CONST             122 (132)
           10137 LOAD_CONST             114 (27)
           10140 LOAD_CONST              59 (21)
           10143 LOAD_CONST             151 (6)
           10146 LOAD_CONST             192 (156)
           10149 LOAD_CONST             142 (116)
           10152 LOAD_CONST             116 (174)
           10155 LOAD_CONST             201 (47)
           10158 LOAD_CONST             149 (16)
           10161 LOAD_CONST             238 (1)
           10164 LOAD_CONST              68 (0)
           10167 LOAD_CONST              33 (219)
           10170 LOAD_CONST             189 (230)
           10173 LOAD_CONST              66 (14)
           10176 LOAD_CONST              53 (228)
           10179 LOAD_CONST              11 (73)
           10182 LOAD_CONST             230 (249)
           10185 LOAD_CONST              89 (134)
           10188 LOAD_CONST              22 (201)
           10191 LOAD_CONST             190 (232)
           10194 LOAD_CONST             133 (114)
           10197 LOAD_CONST              27 (203)
           10200 LOAD_CONST             173 (131)
           10203 LOAD_CONST             153 (33)
           10206 LOAD_CONST              74 (178)
           10209 LOAD_CONST              81 (3)
           10212 LOAD_CONST             146 (29)
           10215 LOAD_CONST             208 (84)
           10218 LOAD_CONST              83 (59)
           10221 LOAD_CONST             245 (89)
           10224 LOAD_CONST              92 (150)
           10227 LOAD_CONST              86 (204)
           10230 LOAD_CONST               2 (48)
           10233 LOAD_CONST              68 (0)
           10236 LOAD_CONST              20 (87)
           10239 LOAD_CONST             205 (42)
           10242 LOAD_CONST             180 (200)
           10245 LOAD_CONST             214 (206)
           10248 LOAD_CONST             155 (94)
           10251 LOAD_CONST              13 (96)
           10254 LOAD_CONST             247 (65)
           10257 LOAD_CONST             160 (154)
           10260 LOAD_CONST             103 (196)
           10263 LOAD_CONST               2 (48)
           10266 LOAD_CONST             102 (231)
           10269 BUILD_LIST            3419
           10272 STORE_NAME               1 (d)

  3        10275 LOAD_CONST             258 ('')
           10278 STORE_NAME               2 (e)

  4        10281 LOAD_CONST              68 (0)
           10284 LOAD_CONST              68 (0)
           10287 BUILD_TUPLE              2
           10290 UNPACK_SEQUENCE          2
           10293 STORE_NAME               3 (i)
           10296 STORE_NAME               4 (j)

  5        10299 LOAD_CONST             165 (83)
           10302 LOAD_CONST               3 (43)
           10305 LOAD_CONST               4 (238)
           10308 LOAD_CONST               5 (211)
           10311 LOAD_CONST               6 (216)
           10314 LOAD_CONST               7 (10)
           10317 LOAD_CONST               8 (57)
           10320 LOAD_CONST               9 (254)
           10323 LOAD_CONST              10 (72)
           10326 LOAD_CONST              94 (76)
           10329 LOAD_CONST              12 (74)
           10332 LOAD_CONST              13 (96)
           10335 LOAD_CONST              14 (182)
           10338 LOAD_CONST              95 (18)
           10341 LOAD_CONST              16 (110)
           10344 LOAD_CONST              17 (210)
           10347 LOAD_CONST              18 (227)
           10350 LOAD_CONST             227 (161)
           10353 LOAD_CONST             166 (243)
           10356 LOAD_CONST             106 (85)
           10359 LOAD_CONST              21 (38)
           10362 LOAD_CONST              22 (201)
           10365 LOAD_CONST              38 (171)
           10368 LOAD_CONST              24 (187)
           10371 LOAD_CONST              25 (189)
           10374 LOAD_CONST              87 (51)
           10377 LOAD_CONST             235 (71)
           10380 LOAD_CONST              27 (203)
           10383 LOAD_CONST              34 (105)
           10386 LOAD_CONST              29 (140)
           10389 LOAD_CONST              30 (126)
           10392 LOAD_CONST              40 (208)
           10395 LOAD_CONST              32 (209)
           10398 LOAD_CONST              33 (219)
           10401 LOAD_CONST             163 (13)
           10404 LOAD_CONST              35 (9)
           10407 LOAD_CONST              36 (64)
           10410 LOAD_CONST              70 (133)
           10413 LOAD_CONST             156 (202)
           10416 LOAD_CONST              38 (171)
           10419 LOAD_CONST             173 (131)
           10422 LOAD_CONST              32 (209)
           10425 LOAD_CONST              41 (169)
           10428 LOAD_CONST             156 (202)
           10431 LOAD_CONST             244 (212)
           10434 LOAD_CONST              44 (155)
           10437 LOAD_CONST              75 (115)
           10440 LOAD_CONST              46 (255)
           10443 LOAD_CONST              47 (102)
           10446 LOAD_CONST              26 (70)
           10449 LOAD_CONST             245 (89)
           10452 LOAD_CONST              50 (141)
           10455 LOAD_CONST              94 (76)
           10458 LOAD_CONST              39 (239)
           10461 LOAD_CONST              53 (228)
           10464 LOAD_CONST             220 (60)
           10467 LOAD_CONST             183 (181)
           10470 LOAD_CONST              55 (224)
           10473 LOAD_CONST              89 (134)
           10476 LOAD_CONST              70 (133)
           10479 LOAD_CONST              58 (24)
           10482 LOAD_CONST             212 (20)
           10485 LOAD_CONST             238 (1)
           10488 LOAD_CONST              61 (157)
           10491 LOAD_CONST              30 (126)
           10494 LOAD_CONST             175 (175)
           10497 LOAD_CONST             121 (36)
           10500 LOAD_CONST              63 (17)
           10503 LOAD_CONST              66 (14)
           10506 LOAD_CONST             238 (1)
           10509 LOAD_CONST              17 (210)
           10512 LOAD_CONST             102 (231)
           10515 LOAD_CONST             171 (8)
           10518 LOAD_CONST              67 (229)
           10521 LOAD_CONST              77 (90)
           10524 LOAD_CONST             230 (249)
           10527 LOAD_CONST              69 (146)
           10530 LOAD_CONST             180 (200)
           10533 LOAD_CONST              37 (225)
           10536 LOAD_CONST              71 (120)
           10539 LOAD_CONST              72 (194)
           10542 LOAD_CONST              92 (150)
           10545 LOAD_CONST              68 (0)
           10548 LOAD_CONST              74 (178)
           10551 LOAD_CONST             184 (31)
           10554 LOAD_CONST             148 (28)
           10557 LOAD_CONST              77 (90)
           10560 LOAD_CONST             203 (58)
           10563 LOAD_CONST             225 (125)
           10566 LOAD_CONST              79 (151)
           10569 LOAD_CONST              27 (203)
           10572 LOAD_CONST             140 (49)
           10575 LOAD_CONST              81 (3)
           10578 LOAD_CONST             120 (86)
           10581 LOAD_CONST              51 (32)
           10584 LOAD_CONST              22 (201)
           10587 LOAD_CONST              67 (229)
           10590 LOAD_CONST             157 (95)
           10593 LOAD_CONST             152 (106)
           10596 LOAD_CONST              36 (64)
           10599 LOAD_CONST              14 (182)
           10602 LOAD_CONST             204 (197)
           10605 LOAD_CONST              87 (51)
           10608 LOAD_CONST             189 (230)
           10611 LOAD_CONST              29 (140)
           10614 LOAD_CONST              90 (50)
           10617 LOAD_CONST              61 (157)
           10620 LOAD_CONST             103 (196)
           10623 LOAD_CONST              92 (150)
           10626 LOAD_CONST             162 (177)
           10629 LOAD_CONST             183 (181)
           10632 LOAD_CONST              94 (76)
           10635 LOAD_CONST              95 (18)
           10638 LOAD_CONST             179 (109)
           10641 LOAD_CONST             145 (121)
           10644 LOAD_CONST              97 (222)
           10647 LOAD_CONST              56 (220)
           10650 LOAD_CONST             100 (240)
           10653 LOAD_CONST              99 (128)
           10656 LOAD_CONST              61 (157)
           10659 LOAD_CONST             199 (136)
           10662 LOAD_CONST              97 (222)
           10665 LOAD_CONST               8 (57)
           10668 LOAD_CONST             186 (234)
           10671 LOAD_CONST             103 (196)
           10674 LOAD_CONST             193 (148)
           10677 LOAD_CONST              59 (21)
           10680 LOAD_CONST             105 (113)
           10683 LOAD_CONST             106 (85)
           10686 LOAD_CONST             109 (119)
           10689 LOAD_CONST             218 (192)
           10692 LOAD_CONST             108 (214)
           10695 LOAD_CONST              38 (171)
           10698 LOAD_CONST             232 (123)
           10701 LOAD_CONST              65 (4)
           10704 LOAD_CONST             232 (123)
           10707 LOAD_CONST               9 (254)
           10710 LOAD_CONST              82 (68)
           10713 LOAD_CONST             105 (113)
           10716 LOAD_CONST             182 (107)
           10719 LOAD_CONST              71 (120)
           10722 LOAD_CONST              24 (187)
           10725 LOAD_CONST             219 (193)
           10728 LOAD_CONST              44 (155)
           10731 LOAD_CONST             114 (27)
           10734 LOAD_CONST              13 (96)
           10737 LOAD_CONST              98 (252)
           10740 LOAD_CONST             115 (215)
           10743 LOAD_CONST             241 (244)
           10746 LOAD_CONST             162 (177)
           10749 LOAD_CONST             118 (62)
           10752 LOAD_CONST             194 (108)
           10755 LOAD_CONST             250 (78)
           10758 LOAD_CONST             106 (85)
           10761 LOAD_CONST             220 (60)
           10764 LOAD_CONST             188 (52)
           10767 LOAD_CONST             122 (132)
           10770 LOAD_CONST             234 (137)
           10773 LOAD_CONST             123 (56)
           10776 LOAD_CONST              72 (194)
           10779 LOAD_CONST              47 (102)
           10782 LOAD_CONST             209 (235)
           10785 LOAD_CONST             126 (54)
           10788 LOAD_CONST             178 (191)
           10791 LOAD_CONST              38 (171)
           10794 LOAD_CONST              87 (51)
           10797 LOAD_CONST              71 (120)
           10800 LOAD_CONST             238 (1)
           10803 LOAD_CONST              51 (32)
           10806 LOAD_CONST              90 (50)
           10809 LOAD_CONST              32 (209)
           10812 LOAD_CONST             129 (100)
           10815 LOAD_CONST             140 (49)
           10818 LOAD_CONST             127 (162)
           10821 LOAD_CONST             103 (196)
           10824 LOAD_CONST              73 (242)
           10827 LOAD_CONST               5 (211)
           10830 LOAD_CONST              98 (252)
           10833 LOAD_CONST             133 (114)
           10836 LOAD_CONST              24 (187)
           10839 LOAD_CONST              79 (151)
           10842 LOAD_CONST               3 (43)
           10845 LOAD_CONST              10 (72)
           10848 LOAD_CONST              27 (203)
           10851 LOAD_CONST             107 (19)
           10854 LOAD_CONST             120 (86)
           10857 LOAD_CONST              83 (59)
           10860 LOAD_CONST              30 (126)
           10863 LOAD_CONST              67 (229)
           10866 LOAD_CONST             185 (172)
           10869 LOAD_CONST              40 (208)
           10872 LOAD_CONST             236 (152)
           10875 LOAD_CONST               5 (211)
           10878 LOAD_CONST             204 (197)
           10881 LOAD_CONST             140 (49)
           10884 LOAD_CONST             158 (226)
           10887 LOAD_CONST             142 (116)
           10890 LOAD_CONST              55 (224)
           10893 LOAD_CONST             207 (2)
           10896 LOAD_CONST             167 (30)
           10899 LOAD_CONST             144 (122)
           10902 LOAD_CONST             145 (121)
           10905 LOAD_CONST             145 (121)
           10908 LOAD_CONST             183 (181)
           10911 LOAD_CONST             103 (196)
           10914 LOAD_CONST             106 (85)
           10917 LOAD_CONST             115 (215)
           10920 LOAD_CONST             147 (221)
           10923 LOAD_CONST             168 (46)
           10926 LOAD_CONST             206 (44)
           10929 LOAD_CONST             148 (28)
           10932 LOAD_CONST              78 (117)
           10935 LOAD_CONST              81 (3)
           10938 LOAD_CONST             150 (247)
           10941 LOAD_CONST               2 (48)
           10944 LOAD_CONST             238 (1)
           10947 LOAD_CONST             152 (106)
           10950 LOAD_CONST             127 (162)
           10953 LOAD_CONST              67 (229)
           10956 LOAD_CONST             154 (143)
           10959 LOAD_CONST             203 (58)
           10962 LOAD_CONST             103 (196)
           10965 LOAD_CONST              91 (199)
           10968 LOAD_CONST             203 (58)
           10971 LOAD_CONST             144 (122)
           10974 LOAD_CONST             157 (95)
           10977 LOAD_CONST              42 (144)
           10980 LOAD_CONST              86 (204)
           10983 LOAD_CONST             122 (132)
           10986 LOAD_CONST             193 (148)
           10989 LOAD_CONST             199 (136)
           10992 LOAD_CONST              48 (34)
           10995 LOAD_CONST             249 (179)
           10998 LOAD_CONST             161 (183)
           11001 LOAD_CONST              53 (228)
           11004 LOAD_CONST              93 (176)
           11007 LOAD_CONST              47 (102)
           11010 LOAD_CONST             207 (2)
           11013 LOAD_CONST              61 (157)
           11016 LOAD_CONST              78 (117)
           11019 LOAD_CONST             182 (107)
           11022 LOAD_CONST              87 (51)
           11025 LOAD_CONST             179 (109)
           11028 LOAD_CONST             166 (243)
           11031 LOAD_CONST             131 (198)
           11034 LOAD_CONST             150 (247)
           11037 LOAD_CONST             166 (243)
           11040 LOAD_CONST             111 (186)
           11043 LOAD_CONST              68 (0)
           11046 LOAD_CONST              89 (134)
           11049 LOAD_CONST             149 (16)
           11052 LOAD_CONST              42 (144)
           11055 LOAD_CONST             178 (191)
           11058 LOAD_CONST             109 (119)
           11061 LOAD_CONST              21 (38)
           11064 BUILD_LIST             255
           11067 STORE_NAME               5 (k)

  6        11070 SETUP_LOOP             101 (to 11174)

  7     >> 11073 LOAD_NAME                3 (i)
           11076 LOAD_NAME                6 (len)
           11079 LOAD_NAME                1 (d)
           11082 CALL_FUNCTION            1
           11085 COMPARE_OP               5 (>=)
           11088 POP_JUMP_IF_FALSE    11095
           11091 BREAK_LOOP          
           11092 JUMP_FORWARD             0 (to 11095)

  8     >> 11095 LOAD_NAME                4 (j)
           11098 LOAD_NAME                6 (len)
           11101 LOAD_NAME                5 (k)
           11104 CALL_FUNCTION            1
           11107 COMPARE_OP               5 (>=)
           11110 POP_JUMP_IF_FALSE    11122
           11113 LOAD_CONST              68 (0)
           11116 STORE_NAME               4 (j)
           11119 JUMP_FORWARD             0 (to 11122)

  9     >> 11122 LOAD_NAME                2 (e)
           11125 LOAD_NAME                7 (chr)
           11128 LOAD_NAME                1 (d)
           11131 LOAD_NAME                3 (i)
           11134 BINARY_SUBSCR       
           11135 LOAD_NAME                5 (k)
           11138 LOAD_NAME                4 (j)
           11141 BINARY_SUBSCR       
           11142 BINARY_XOR          
           11143 CALL_FUNCTION            1
           11146 INPLACE_ADD         
           11147 STORE_NAME               2 (e)

 10        11150 LOAD_NAME                3 (i)
           11153 LOAD_CONST             238 (1)
           11156 INPLACE_ADD         
           11157 STORE_NAME               3 (i)

 11        11160 LOAD_NAME                4 (j)
           11163 LOAD_CONST             238 (1)
           11166 INPLACE_ADD         
           11167 STORE_NAME               4 (j)
           11170 JUMP_ABSOLUTE        11073
           11173 POP_BLOCK           

 12     >> 11174 LOAD_NAME                0 (marshal)
           11177 LOAD_ATTR                8 (loads)
           11180 LOAD_NAME                2 (e)
           11183 CALL_FUNCTION            1
           11186 LOAD_CONST               1 (None)
           11189 DUP_TOP             
           11190 EXEC_STMT           
           11191 LOAD_CONST               1 (None)
           11194 RETURN_VALUE        
   consts
      -1
      None
      48
      43
      238
      211
      216
      10
      57
      254
      72
      73
      74
      96
      182
      82
      110
      210
      227
      7
      87
      38
      201
      207
      187
      189
      70
      203
      5
      140
      126
      138
      209
      219
      105
      9
      64
      225
      171
      239
      208
      169
      144
      213
      155
      23
      255
      102
      34
      91
      141
      32
      237
      228
      81
      224
      220
      129
      24
      21
      101
      157
      39
      17
      98
      4
      14
      229
      0
      146
      133
      120
      194
      242
      178
      115
      25
      90
      117
      151
      145
      3
      68
      59
      111
      218
      204
      51
      139
      134
      50
      199
      150
      176
      76
      18
      127
      222
      252
      128
      240
      99
      231
      196
      149
      113
      85
      19
      214
      119
      22
      186
      165
      147
      27
      215
      174
      190
      62
      79
      86
      36
      132
      56
      12
      250
      54
      162
      251
      100
      40
      198
      184
      114
      35
      45
      55
      173
      153
      205
      49
      97
      116
      112
      122
      121
      29
      221
      28
      16
      247
      6
      106
      33
      143
      94
      202
      95
      226
      241
      154
      183
      177
      13
      246
      83
      243
      30
      46
      11
      195
      8
      37
      131
      168
      175
      135
      253
      191
      109
      200
      248
      107
      181
      31
      172
      234
      160
      52
      230
      232
      180
      156
      148
      108
      104
      245
      63
      92
      136
      93
      47
      69
      58
      197
      42
      44
      2
      84
      235
      142
      170
      20
      124
      206
      67
      223
      26
      192
      193
      60
      130
      159
      61
      15
      125
      103
      161
      233
      77
      249
      164
      123
      118
      137
      71
      152
      41
      1
      163
      185
      244
      217
      75
      212
      89
      236
      65
      80
      179
      78
      66
      88
      167
      53
      188
      166
      158
      ''
   names ('marshal', 'd', 'e', 'i', 'j', 'k', 'len', 'chr', 'loads')
   varnames ()
   freevars ()
   cellvars ()
   filename '<script>'
   name '<module>'
   firstlineno 1
   lnotab
      0c01ff00ff00ff00ff00ff00ff00ff00ff00ff00ff00ff00ff00ff00ff00
      ff00ff00ff00ff00ff00ff00ff00ff00ff00ff00ff00ff00ff00ff00ff00
      ff00ff00ff00ff00ff00ff00ff00ff00ff00ff00ff003f0106011201ff00
      ff00ff000601030112000401120009011c010a010e01
